{
  "timestamp": "2025-06-14T04:33:23.731Z",
  "walkerPlusSource": "ar0400-hanabi-list.json",
  "localRegion": "koshinetsu",
  "regionName": "甲信越",
  "analysis": {
    "region": "koshinetsu",
    "summary": {
      "matches": 3,
      "walkerPlusOnly": 18,
      "localOnly": 5,
      "totalWalkerPlus": 21,
      "totalLocal": 8,
      "matchRate": "14.3"
    },
    "matches": [
      {
        "walkerPlus": {
          "title": "第119回 長野えびす講煙火大会",
          "date": "2025年11月23日",
          "location": "新潟県・長岡市/信濃川河川敷",
          "visitors": "40万人",
          "fireworks": "2万発",
          "rawText": "第119回 長野えびす講煙火大会\n                      \n                      \n                        \n                        \n                      \n                      \n                        \n                          信州の澄んだ夜空を彩る晩秋の花火\n                          長野県・長野市/長野大橋西側  犀川第2緑地\n                          期間：2025年11月23日(日)\n                            \n                              例年の人出：約40万人\n                              行ってみたい：23\n                              行ってよかった：11\n                              \n                              有料席：あり\n                              屋台：あり\n                            \n                          \n                        \n                      \n                    \n                  \n                \n                \n                \n                \n                  \n                    \n                      \n                        \n                        長岡まつり大花火大会\n                      \n                      \n                        \n                        \n                      \n                      \n                        \n                          復興祈願花火フェニックスは、ほかにはない大迫力\n                          新潟県・長岡市/信濃川河川敷\n                          期間：2025年8月2日(土)・3日(日)\n                            \n                              例年の人出：約34万5000人\n                              行ってみたい：81\n                              行ってよかった：42\n                              \n                              有料席：あり\n                              屋台：あり\n                            \n                          \n                        \n                      \n                    \n                  \n                \n                \n                \n                \n                  \n                    \n                      \n                        \n                        新潟まつり花火大会\n                      \n                      \n                        \n                        \n                      \n                      \n                        \n                          日本一の大河「信濃川」を舞台に繰り広げられる壮大な花火大会\n                          新潟県・新潟市中央区/新潟市中央区信濃川河畔(昭和大橋周辺)\n                          期間：2025年8月10日(日)\n                            \n                              例年の人出：約32万人\n                              行ってみたい：20\n                              行ってよかった：7\n                              \n                              \n                              \n                            \n                          \n                        \n                      \n                    \n                  \n                \n                \n\n\n\n\n\n                \n                \n                  \n                    \n                      \n                        \n                        全国新作花火チャレンジカップ2025\n                      \n                      \n                        \n                        \n                      \n                      \n                        \n                          6年ぶりにリニューアルし、分散方式による競技花火を開催決定\n                          長野県・諏訪市/長野県諏訪市湖畔公園前諏訪湖上\n                          期間：予選：2025年9月6日(土)・13日(土)・20日(土)・27日(土)。決勝：10月26日(日)\n                            \n                              例年の人出：約25万人\n                              行ってみたい：7\n                              行ってよかった：2\n                              \n                              \n                              \n                            \n                          \n                        \n                      \n                    \n                  \n                \n                \n                \n                \n                  \n                    \n                      \n                        \n                        市川三郷町ふるさと夏まつり　第37回「神明の花火大会」\n                      \n                      \n                        \n                        \n                      \n                      \n                        \n                          音楽と彩る約2万発の夜空の芸術\n                          山梨県・西八代郡市川三郷町/三郡橋下流笛吹川河畔\n                          期間：2025年8月7日(木)\n                            \n                              例年の人出：約20万人\n                              行ってみたい：28\n                              行ってよかった：20\n                              \n                              有料席：あり\n                              屋台：あり\n                            \n                          \n                        \n                      \n                    \n                  \n                \n                \n                \n                \n                  \n                    \n                      \n                        \n                        第51回 阿賀野川ござれや花火\n                      \n                      \n                        \n                        \n                      \n                      \n                        \n                          超特大スターマインの花鳥風月をお見逃しなく\n                          新潟県・新潟市北区/阿賀野川松浜橋上流側\n                          期間：2025年8月25日(月)\n                            \n                              例年の人出：20万人\n                              行ってみたい：7\n                              行ってよかった：5\n                              \n                              有料席：あり\n                              \n                            \n                          \n                        \n                      \n                    \n                  \n                \n                \n\n\n\n\n\n\n                \n                \n                  \n                    \n                      \n                        \n                        おぢやまつり大花火大会2024\n                      \n                      \n                        \n                        \n                      \n                      \n                        \n                          超ワイド大スターマインが夜空に咲く\n                          新潟県・小千谷市/信濃川河川敷(旭橋下流)\n                          期間：2024年8月24日(土)おぢやまつりは8月23日(金)～25日(日)の3日間\n                            \n                              例年の人出：18万人\n                              行ってみたい：5\n                              行ってよかった：2\n                              \n                              有料席：あり\n                              \n                            \n                          \n                        \n                      \n                    \n                  \n                \n                \n                \n                \n                  \n                    \n                      \n                        \n                        ぎおん柏崎まつり 海の大花火大会\n                      \n                      \n                        \n                        \n                      \n                      \n                        \n                          尺玉100発一斉打上など豪華な花火がめじろ押し\n                          新潟県・柏崎市/柏崎市中央海岸・みなとまち海浜公園一帯\n                          期間：2025年7月26日(土)\n                            \n                              例年の人出：約17万人\n                              行ってみたい：24\n                              行ってよかった：18\n                              \n                              有料席：あり\n                              屋台：あり\n                            \n                          \n                        \n                      \n                    \n                  \n                \n                \n                \n                \n                  \n                    \n                      \n                        \n                        浅原神社 秋季例大祭奉納大煙火\n                      \n                      \n                        \n                        \n                      \n                      \n                        \n                          四尺玉をはじめ尺玉多数、大迫力の尺玉連発を堪能\n                          新潟県・小千谷市/片貝町浅原神社裏手\n                          期間：2025年9月12日(金)・13日(土)\n                            \n                              例年の人出：約17万人\n                              行ってみたい：15\n                              行ってよかった：11\n                              \n                              有料席：あり\n                              屋台：あり\n                            \n                          \n                        \n                      \n                    \n                  \n                \n                \n                \n                \n                  \n                    \n                      \n                        \n                        河口湖湖上祭\n                      \n                      \n                        \n                        \n                      \n                      \n                        \n                          河口湖の夜空を彩る大迫力の花火\n                          山梨県・南都留郡富士河口湖町/河口湖畔船津浜\n                          期間：2025年8月5日(火)\n                            \n                              例年の人出：12万人\n                              行ってみたい：24\n                              行ってよかった：8\n                              \n                              \n                              屋台：あり"
        },
        "local": {
          "id": "nagano-ebisukou-hanabi-2025",
          "name": "第119回长野惠比寿讲烟火大会",
          "date": "2025年11月23日",
          "location": "长野県・长野市/长野大桥西侧 犀川第2绿地",
          "visitors": 400000,
          "fireworks": 40000
        }
      },
      {
        "walkerPlus": {
          "title": "ぎおん柏崎まつり 海の大花火大会",
          "date": "2025年7月26日",
          "location": "新潟県・柏崎市/柏崎市中央海岸・みなとまち海浜公園一帯",
          "visitors": "17万人",
          "fireworks": "100発",
          "rawText": "ぎおん柏崎まつり 海の大花火大会\n                      \n                      \n                        \n                        \n                      \n                      \n                        \n                          尺玉100発一斉打上など豪華な花火がめじろ押し\n                          新潟県・柏崎市/柏崎市中央海岸・みなとまち海浜公園一帯\n                          期間：2025年7月26日(土)\n                            \n                              例年の人出：約17万人\n                              行ってみたい：24\n                              行ってよかった：18\n                              \n                              有料席：あり\n                              屋台：あり"
        },
        "local": {
          "id": "gion-kashiwazaki-matsuri-hanabi",
          "name": "祇园柏崎祭海之大花火大会",
          "date": "2025年7月26日",
          "location": "新潟県・柏崎市/中央海岸",
          "visitors": 170000,
          "fireworks": 15000
        }
      },
      {
        "walkerPlus": {
          "title": "河口湖の夜空を彩る大迫力の花火",
          "date": "2025年8月5日",
          "location": "山梨県・南都留郡富士河口湖町/河口湖畔船津浜",
          "visitors": "12万人",
          "fireworks": "",
          "rawText": "河口湖の夜空を彩る大迫力の花火\n                          山梨県・南都留郡富士河口湖町/河口湖畔船津浜\n                          期間：2025年8月5日(火)\n                            \n                              例年の人出：12万人\n                              行ってみたい：24\n                              行ってよかった：8\n                              \n                              \n                              屋台：あり"
        },
        "local": {
          "id": "fuji-kawaguchi-lake-hanabi",
          "name": "富士山河口湖山开花火大会",
          "date": "2025年7月5日",
          "location": "山梨県・南都留郡富士河口湖町/大池公园主会场",
          "visitors": 50000,
          "fireworks": 10000
        }
      }
    ],
    "walkerPlusOnly": [
      {
        "title": "甲信越の花火大会の人出ランキング - 花火大会2025 - ウォーカープラス",
        "date": "2024年8月9日",
        "location": "新潟県\"",
        "visitors": "20万人",
        "fireworks": "2万発",
        "rawText": "甲信越の花火大会の人出ランキング - 花火大会2025 - ウォーカープラス\n  \n  \n  \n  \n  \n  \n  \n  \n\n  \n  \n  \n  \n  \n  \n  \n  \n  \n  \n  \n  \n\n  \n  \n  \n  \n  \n  \n  \n  \n  \n  \n  \n\n  \n  \n  \n\n[\n\n  {\n    \"@context\" : \"http://schema.org\", \"@type\" : \"Event\",\n    \"name\" : \"第119回 長野えびす講煙火大会\",\n  \n      \"startDate\" : \"2025-11-23\",\n  \n  \n      \"endDate\" : \"2025-11-23\",\n  \n    \"eventAttendanceMode\": \"https://schema.org/OfflineEventAttendanceMode\",\n    \"location\": {\n      \"@type\": \"Place\",\n      \"name\": \"長野大橋西側  犀川第2緑地\",\n      \"address\" : {\n          \"@type\" : \"PostalAddress\",\n          \"addressLocality\" : \"長野市\",\n          \"addressRegion\" : \"長野県\"\n      }\n    },\n    \"image\" : \"https://image.walkerplus.com/wpimg/walkertouch/wtd/event/12/l2/1112_4.jpg\",\n    \"description\": \"長野県長野市で行われる、全国でも珍しい11月の花火大会。1899年(明治32年)に始まり、善光寺の門前町として発展してきた、長野の歴史と伝統を誇る。熟練の煙火師のみを大会に参加させたことから、「出世煙火」といわれるようになり、現在でも良質な花火を打ち上げる全国有数の大会の一つに数えられている。\",\n    \"url\" : \"https://hanabi.walkerplus.com/detail/ar0420e01112/\"\n  },\n\n  {\n    \"@context\" : \"http://schema.org\", \"@type\" : \"Event\",\n    \"name\" : \"長岡まつり大花火大会\",\n  \n      \"startDate\" : \"2025-08-02\",\n  \n  \n      \"endDate\" : \"2025-08-03\",\n  \n    \"eventAttendanceMode\": \"https://schema.org/OfflineEventAttendanceMode\",\n    \"location\": {\n      \"@type\": \"Place\",\n      \"name\": \"信濃川河川敷\",\n      \"address\" : {\n          \"@type\" : \"PostalAddress\",\n          \"addressLocality\" : \"長岡市\",\n          \"addressRegion\" : \"新潟県\"\n      }\n    },\n    \"image\" : \"https://image.walkerplus.com/wpimg/walkertouch/wtd/event/65/l2/665.jpg\",\n    \"description\": \"例年8月2日・3日に開催される、長岡空襲で亡くなった方々への慰霊と復興に尽力した先人への感謝、恒久平和への願いなど、度重なる苦難を乗り越えてきた長岡市民の特別な想いが込められた花火大会。信濃川の両岸に観覧席が設けられており、両方向から花火を観ることができる。その特性を活かし、尺玉を多用した演出が多い稀有な存在の花火大会だ。\",\n    \"url\" : \"https://hanabi.walkerplus.com/detail/ar0415e00665/\"\n  },\n\n  {\n    \"@context\" : \"http://schema.org\", \"@type\" : \"Event\",\n    \"name\" : \"新潟まつり花火大会\",\n  \n      \"startDate\" : \"2025-08-10\",\n  \n  \n      \"endDate\" : \"2025-08-10\",\n  \n    \"eventAttendanceMode\": \"https://schema.org/OfflineEventAttendanceMode\",\n    \"location\": {\n      \"@type\": \"Place\",\n      \"name\": \"新潟市中央区信濃川河畔(昭和大橋周辺)\",\n      \"address\" : {\n          \"@type\" : \"PostalAddress\",\n          \"addressLocality\" : \"新潟市中央区\",\n          \"addressRegion\" : \"新潟県\"\n      }\n    },\n    \"image\" : \"https://image.walkerplus.com/wpimg/walkertouch/wtd/event/66/l2/666_2.jpg\",\n    \"description\": \"【※大会プログラムは過去の情報になります。開催予定の大会については詳細が決定次第、情報を更新します】2024年8月9日(金)から11日(祝)の3日間にわたり開催される新潟まつりは、新潟を代表する夏の風物詩。そのフィナーレを飾る花火大会では、音楽花火や、迫力満点のワイドスターマインなどが観客を楽しませる。バーチャル・シンガーとして世界中で人気を集めている「初音ミク」とのコラボレーションも見もの。日本一長い川として知られる信濃川を舞台に、都心部で音楽と花火が共演する優美な景観を堪能できる。\",\n    \"url\" : \"https://hanabi.walkerplus.com/detail/ar0415e00666/\"\n  },\n\n  {\n    \"@context\" : \"http://schema.org\", \"@type\" : \"Event\",\n    \"name\" : \"全国新作花火チャレンジカップ2025\",\n  \n      \"startDate\" : \"2025-09-06\",\n  \n  \n      \"endDate\" : \"2025-10-26\",\n  \n    \"eventAttendanceMode\": \"https://schema.org/OfflineEventAttendanceMode\",\n    \"location\": {\n      \"@type\": \"Place\",\n      \"name\": \"長野県諏訪市湖畔公園前諏訪湖上\",\n      \"address\" : {\n          \"@type\" : \"PostalAddress\",\n          \"addressLocality\" : \"諏訪市\",\n          \"addressRegion\" : \"長野県\"\n      }\n    },\n    \"image\" : \"/asset/core/images/noimg.gif\",\n    \"description\": \"2019年を最後に中止・見送りとなっていた「全国新作花火競技大会」が大会名を「全国新作花火チャレンジカップ2025」に変更し、開催方式も分散型として6年ぶりに開催が決定。全国から選抜された20名の煙火師で9月に予選4回を実施し、各回の1位と、2位の中で最上位者の計5名により10月に決勝を行う。煙火師は従来の技術にとらわれず、思い描いたイメージ「コメント」に合わせて競い、2025年度の優勝者を決定する。今年度は、「色彩が優れ、華麗であること」をテーマとする。\",\n    \"url\" : \"https://hanabi.walkerplus.com/detail/ar0420e00806/\"\n  },\n\n  {\n    \"@context\" : \"http://schema.org\", \"@type\" : \"Event\",\n    \"name\" : \"市川三郷町ふるさと夏まつり　第37回「神明の花火大会」\",\n  \n      \"startDate\" : \"2025-08-07\",\n  \n  \n      \"endDate\" : \"2025-08-07\",\n  \n    \"eventAttendanceMode\": \"https://schema.org/OfflineEventAttendanceMode\",\n    \"location\": {\n      \"@type\": \"Place\",\n      \"name\": \"三郡橋下流笛吹川河畔\",\n      \"address\" : {\n          \"@type\" : \"PostalAddress\",\n          \"addressLocality\" : \"西八代郡市川三郷町\",\n          \"addressRegion\" : \"山梨県\"\n      }\n    },\n    \"image\" : \"https://image.walkerplus.com/wpimg/walkertouch/wtd/event/10/l2/910.jpg\",\n    \"description\": \"山梨県市川三郷町で毎年、花火の日である8月7日に開催される大会。県内最大級の規模を誇り、約2万発の花火が三郡橋下流の笛吹川河畔から打ち上げられる。大会では音楽と連動した構成が大きな魅力で、視覚と聴覚を融合させたストーリー仕立ての演出が夜空を華やかに染める。例年約20万人が訪れる人気イベントで、会場周辺には約80の屋台が並び、グルメも楽しめる。当日は混雑が予想されるため、公共交通機関の利用や早めの移動が望ましい。有料観覧席も充実しており、場所取りのストレスなくゆったりと鑑賞したい人におすすめだ。\",\n    \"url\" : \"https://hanabi.walkerplus.com/detail/ar0419e00910/\"\n  },\n\n  {\n    \"@context\" : \"http://schema.org\", \"@type\" : \"Event\",\n    \"name\" : \"第51回 阿賀野川ござれや花火\",\n  \n      \"startDate\" : \"2025-08-25\",\n  \n  \n      \"endDate\" : \"2025-08-25\",\n  \n    \"eventAttendanceMode\": \"https://schema.org/OfflineEventAttendanceMode\",\n    \"location\": {\n      \"@type\": \"Place\",\n      \"name\": \"阿賀野川松浜橋上流側\",\n      \"address\" : {\n          \"@type\" : \"PostalAddress\",\n          \"addressLocality\" : \"新潟市北区\",\n          \"addressRegion\" : \"新潟県\"\n      }\n    },\n    \"image\" : \"https://image.walkerplus.com/wpimg/walkertouch/wtd/images/l2/73675.jpg\",\n    \"description\": \"【※大会プログラムは過去の情報になります。開催予定の大会については詳細が決定次第、情報を更新します】新潟県で流れる阿賀野川で開催される花火大会。2024年のテーマは「誇～ひとり一人の心根に咲く花を。これからも～」で、「未来の子どもたちに誇れる花火大会を創る」という思いが込められる。今年は50回の記念大会でもあり、通常開催として実施。色とりどりなスターマインで始まり、2尺玉、大切な方へのお祝い花火、夏をテーマに小学生約1070人から選ばれたデザイン花火5作品などが打ち上げられる。公式YouTubeチャンネルによる無料ライブ中継もある。\",\n    \"url\" : \"https://hanabi.walkerplus.com/detail/ar0415e00061/\"\n  },\n\n  {\n    \"@context\" : \"http://schema.org\", \"@type\" : \"Event\",\n    \"name\" : \"おぢやまつり大花火大会2024\",\n  \n      \"startDate\" : \"2024-08-24\",\n  \n  \n      \"endDate\" : \"2024-08-24\",\n  \n    \"eventAttendanceMode\": \"https://schema.org/OfflineEventAttendanceMode\",\n    \"location\": {\n      \"@type\": \"Place\",\n      \"name\": \"信濃川河川敷(旭橋下流)\",\n      \"address\" : {\n          \"@type\" : \"PostalAddress\",\n          \"addressLocality\" : \"小千谷市\",\n          \"addressRegion\" : \"新潟県\"\n      }\n    },\n    \"image\" : \"https://image.walkerplus.com/wpimg/walkertouch/wtd/images/l2/154204.jpg\",\n    \"description\": \"新潟県小千谷市の最大の祭り「おぢやまつり」で開催される大花火大会。「おぢやまつり」は3日間の日程で行われ、注目は8月24日(土)・25日(日)に行われる「からくり万灯パレード」と、24日(土)に行われる「大花火大会」。約7000発の花火が打ち上げられる「大花火大会」は、新潟県内屈指の花火大会でもある。\",\n    \"url\" : \"https://hanabi.walkerplus.com/detail/ar0415e00060/\"\n  },\n\n  {\n    \"@context\" : \"http://schema.org\", \"@type\" : \"Event\",\n    \"name\" : \"ぎおん柏崎まつり 海の大花火大会\",\n  \n      \"startDate\" : \"2025-07-26\",\n  \n  \n      \"endDate\" : \"2025-07-26\",\n  \n    \"eventAttendanceMode\": \"https://schema.org/OfflineEventAttendanceMode\",\n    \"location\": {\n      \"@type\": \"Place\",\n      \"name\": \"柏崎市中央海岸・みなとまち海浜公園一帯\",\n      \"address\" : {\n          \"@type\" : \"PostalAddress\",\n          \"addressLocality\" : \"柏崎市\",\n          \"addressRegion\" : \"新潟県\"\n      }\n    },\n    \"image\" : \"https://image.walkerplus.com/wpimg/walkertouch/wtd/event/63/l2/663_1.jpg\",\n    \"description\": \"新潟県柏崎市の夏を代表する一大花火イベント。川の長岡、山の片貝、海の柏崎と、越後三大花火の一つに数えられている。新型コロナウイルスのまん延により2年連続で中止になっていたが、2022年に3年ぶりに開催された。2025年も、1万6000発の花火が柏崎の夜空に打ちあがる。\",\n    \"url\" : \"https://hanabi.walkerplus.com/detail/ar0415e00663/\"\n  },\n\n  {\n    \"@context\" : \"http://schema.org\", \"@type\" : \"Event\",\n    \"name\" : \"浅原神社 秋季例大祭奉納大煙火\",\n  \n      \"startDate\" : \"2025-09-12\",\n  \n  \n      \"endDate\" : \"2025-09-13\",\n  \n    \"eventAttendanceMode\": \"https://schema.org/OfflineEventAttendanceMode\",\n    \"location\": {\n      \"@type\": \"Place\",\n      \"name\": \"片貝町浅原神社裏手\",\n      \"address\" : {\n          \"@type\" : \"PostalAddress\",\n          \"addressLocality\" : \"小千谷市\",\n          \"addressRegion\" : \"新潟県\"\n      }\n    },\n    \"image\" : \"https://image.walkerplus.com/wpimg/walkertouch/wtd/images/l2/74205.jpg\",\n    \"description\": \"三尺玉の発祥地として知られる新潟県小千谷市片貝町で200年の伝統を誇る「片貝まつり奉納大煙火」。最大の注目は世界最大とされる四尺玉花火の打ち上げで、ほかにはないスケール感を生で味わえる。三尺玉の木筒を引っ張る「筒引き」や「玉送り」といった花火にまつわる伝統行事も行われ、町中が花火一色となる。\",\n    \"url\" : \"https://hanabi.walkerplus.com/detail/ar0415e00667/\"\n  },\n\n  {\n    \"@context\" : \"http://schema.org\", \"@type\" : \"Event\",\n    \"name\" : \"河口湖湖上祭\",\n  \n      \"startDate\" : \"2025-08-05\",\n  \n  \n      \"endDate\" : \"2025-08-05\",\n  \n    \"eventAttendanceMode\": \"https://schema.org/OfflineEventAttendanceMode\",\n    \"location\": {\n      \"@type\": \"Place\",\n      \"name\": \"河口湖畔船津浜\",\n      \"address\" : {\n          \"@type\" : \"PostalAddress\",\n          \"addressLocality\" : \"南都留郡富士河口湖町\",\n          \"addressRegion\" : \"山梨県\"\n      }\n    },\n    \"image\" : \"https://image.walkerplus.com/wpimg/walkertouch/wtd/images/l2/73646.jpg\",\n    \"description\": \"1917年(大正6年)から続く河口湖湖上祭は、夏の河口湖の代名詞となっており、数ある富士五湖の夏祭りの中でも最大規模の花火大会である。雄大な富士山を背景にミュージカル花火、大型打ち上げ花火など約1万発の打ち上げ花火が、水面にも美しく映える。\",\n    \"url\" : \"https://hanabi.walkerplus.com/detail/ar0419e00681/\"\n  }\n\n]\n\n  \n\n\n\nvar area = (/ar[0-9]{4}/g.exec(location.pathname));\narea = (area == null)? '' : area[0];\n\nif(area == \"\" && document.querySelector('meta[name=ad_dfp_area]')){\narea = document.getElementsByName('ad_dfp_area')[0].getAttribute('code');\n}\n\nwindow.googletag = window.googletag || {cmd: []};\ngoogletag.cmd.push(function() {\ngoogletag.defineSlot('/11970315/hanabi_all_ol_gam', [728, 90], 'hanabi_all_ol_gam').addService(googletag.pubads());\ngoogletag.defineSlot('/11970315/hanabi_all_bb_gam', [[728, 90], [970, 250]], 'hanabi_all_bb_gam').setCollapseEmptyDiv(true).addService(googletag.pubads());\ngoogletag.defineSlot('/11970315/hanabi_all_1r_gam', [[300, 250], [300, 600]], 'hanabi_all_1r_gam').setCollapseEmptyDiv(true).addService(googletag.pubads());\ngoogletag.defineSlot('/11970315/hanabi_list_infeed1_gam', ['fluid'], 'hanabi_list_infeed1_gam').addService(googletag.pubads());\ngoogletag.defineSlot('/11970315/hanabi_list_infeed2_gam', ['fluid'], 'hanabi_list_infeed2_gam').addService(googletag.pubads());\ngoogletag.defineSlot('/11970315/hanabi_list_infeed3_gam', ['fluid'], 'hanabi_list_infeed3_gam').addService(googletag.pubads());\ngoogletag.defineSlot('/11970315/hanabi_all_3r_gam', [300, 250], 'hanabi_all_3r_gam').addService(googletag.pubads());\ngoogletag.defineSlot('/11970315/hanabi_all_4r_gam', [300, 250], 'hanabi_all_4r_gam').addService(googletag.pubads());\ngoogletag.defineSlot('/11970315/hanabi_all_2r_gam', [[300, 250], [300, 600]], 'hanabi_all_2r_gam').addService(googletag.pubads());\ngoogletag.defineSlot('/11970315/hanabi_iat1', ['fluid'], 'hanabi_iat1').addService(googletag.pubads());\ngoogletag.defineSlot('/11970315/hanabi_iat2', ['fluid'], 'hanabi_iat2').addService(googletag.pubads());\ngoogletag.defineSlot('/11970315/hanabi_all_iat3_gam', ['fluid'], 'hanabi_all_iat3_gam').addService(googletag.pubads());\ngoogletag.defineSlot('/11970315/hanabi_all_iat4_gam', ['fluid'], 'hanabi_all_iat4_gam').addService(googletag.pubads());\ngoogletag.defineSlot('/11970315/hanabi_all_sidebnr1_gam', [170, 1024], 'hanabi_all_sidebnr1_gam').addService(googletag.pubads()); //純広告配信時のみ使用\ngoogletag.defineSlot('/11970315/hanabi_all_sidebnr2_gam', [170, 1024], 'hanabi_all_sidebnr2_gam').addService(googletag.pubads()); //純広告配信時のみ使用\ngoogletag.pubads().setTargeting('page-environment', [(location.hostname==\"hanabi.walkerplus.com\")? '': 'test'])\ngoogletag.pubads().setTargeting('area', [area]);\ngoogletag.pubads().enableSingleRequest();\ngoogletag.pubads().collapseEmptyDivs();\ngoogletag.enableServices();\n});\n\n\n\n\n\n  \n  \n<iframe src=\"//www.googletagmanager.com/ns.html?id=GTM-MFFS32\"\n        height=\"0\" width=\"0\" style=\"display:none;visibility:hidden\"></iframe>\n(function(w,d,s,l,i){w[l]=w[l]||[];w[l].push({'gtm.start':\n    new Date().getTime(),event:'gtm.js'});var f=d.getElementsByTagName(s)[0],\nj=d.createElement(s),dl=l!='dataLayer'?'&l='+l:'';j.async=true;j.src=\n'//www.googletagmanager.com/gtm.js?id='+i+dl;f.parentNode.insertBefore(j,f);\n})(window,document,'script','dataLayer','GTM-MFFS32');\n\n  \n  \n    \n      \n      \n        \n  \n    \n      \n.plus {fill:url(#gradient);}.font {fill: #fff; }\n            \n            \n          \n\n\n\n\n\n\n\n\n\n\n\n\n\n\n\n\n\n\n\n\n\n\n\n\n\n\n\n\n\n\n\n\n\n      \n    \n    \n      \n      \n    \n    \n  \n\n\n        \n\n\n\n全国約900大会の花火大会情報をお届け！\n\n \n\n\n \n    \n    \n    \n    \n\n                  \n            \n              \n                \n                  花火特集2025\n                  北海道\n                  東北\n                  関東\n                    \n                      東京\n                      神奈川\n                      千葉\n                    \n                  \n                  甲信越\n                  北陸\n                  東海\n                  \n                      愛知\n                    \n                   \n                  関西\n                    \n                      大阪\n                    \n                  \n                  中国\n                  四国\n                  九州・沖縄\n                \n              \n                         \n                \n                エリアから探す\n                \n                人気ランキング\n           \t\t\n                開催予定の花火大会\n                花火カレンダー\n                \n                おうちで金麦\n                \n              \n              \n\n    \t\t\t\n\n\n\n  \n  \n    \n      \n\n\n\n\t\n    \n    \n      \n\n\n\n    \n    \n  \n\n\n\n            \n          \n        \n\n\n\n\n\n\n\n\n\n        \n   2025年の情報に順次更新しておりますが、過去の情報もございます。当日の開催情報は大会主催者に確認ください \n\n\n\n                \n          \n          \n            \n              \n              花火大会2025\n            \n            \n          \n          \n          \n            \n              \n              全国の花火大会の人出ランキング\n            \n            \n          \n          \n          \n            \n              \n              甲信越の花火大会の人出ランキング\n            \n            \n          \n          \n        \n     \n      \n    \n    \n      \n        \n          \n              \n\n            \n            \n              \n                甲信越の花火大会の人出ランキング\n                例年の来場者数をもとにランキング！混雑を予測しておでかけの参考にしよう！\n              \n              \n              \n    \n        注目の花火大会\n        \n          河口湖湖上祭長岡まつり大花火大会\n        \n    \n\n              2025年6月14日 更新\n              エリアを絞り込む\n              \n                \n                \n                甲信越\n                \n                山梨県\n                \n                \n                長野県\n                \n                \n                新潟県\n                \n              \n              その他のランキングから探す\n              \n                \n                  \n                    人気花火大会ランキング\n                    \n                        打ち上げ数ランキング\n                      \n                  \n                  \n                    \n                        行ってみたいランキング\n                      \n                    \n                        行ってよかったランキング\n                      \n                  \n                \n              \n\n              \n              \n                \n                \n                  \n                    \n                      \n                        \n                        第119回 長野えびす講煙火大会\n                      \n                      \n                        \n                        \n                      \n                      \n                        \n                          信州の澄んだ夜空を彩る晩秋の花火\n                          長野県・長野市/長野大橋西側  犀川第2緑地\n                          期間：2025年11月23日(日)\n                            \n                              例年の人出：約40万人\n                              行ってみたい：23\n                              行ってよかった：11\n                              \n                              有料席：あり\n                              屋台：あり\n                            \n                          \n                        \n                      \n                    \n                  \n                \n                \n                \n                \n                  \n                    \n                      \n                        \n                        長岡まつり大花火大会\n                      \n                      \n                        \n                        \n                      \n                      \n                        \n                          復興祈願花火フェニックスは、ほかにはない大迫力\n                          新潟県・長岡市/信濃川河川敷\n                          期間：2025年8月2日(土)・3日(日)\n                            \n                              例年の人出：約34万5000人\n                              行ってみたい：81\n                              行ってよかった：42\n                              \n                              有料席：あり\n                              屋台：あり\n                            \n                          \n                        \n                      \n                    \n                  \n                \n                \n                \n                \n                  \n                    \n                      \n                        \n                        新潟まつり花火大会\n                      \n                      \n                        \n                        \n                      \n                      \n                        \n                          日本一の大河「信濃川」を舞台に繰り広げられる壮大な花火大会\n                          新潟県・新潟市中央区/新潟市中央区信濃川河畔(昭和大橋周辺)\n                          期間：2025年8月10日(日)\n                            \n                              例年の人出：約32万人\n                              行ってみたい：20\n                              行ってよかった：7\n                              \n                              \n                              \n                            \n                          \n                        \n                      \n                    \n                  \n                \n                \n\n\n\n\n\n                \n                \n                  \n                    \n                      \n                        \n                        全国新作花火チャレンジカップ2025\n                      \n                      \n                        \n                        \n                      \n                      \n                        \n                          6年ぶりにリニューアルし、分散方式による競技花火を開催決定\n                          長野県・諏訪市/長野県諏訪市湖畔公園前諏訪湖上\n                          期間：予選：2025年9月6日(土)・13日(土)・20日(土)・27日(土)。決勝：10月26日(日)\n                            \n                              例年の人出：約25万人\n                              行ってみたい：7\n                              行ってよかった：2\n                              \n                              \n                              \n                            \n                          \n                        \n                      \n                    \n                  \n                \n                \n                \n                \n                  \n                    \n                      \n                        \n                        市川三郷町ふるさと夏まつり　第37回「神明の花火大会」\n                      \n                      \n                        \n                        \n                      \n                      \n                        \n                          音楽と彩る約2万発の夜空の芸術\n                          山梨県・西八代郡市川三郷町/三郡橋下流笛吹川河畔\n                          期間：2025年8月7日(木)\n                            \n                              例年の人出：約20万人\n                              行ってみたい：28\n                              行ってよかった：20\n                              \n                              有料席：あり\n                              屋台：あり\n                            \n                          \n                        \n                      \n                    \n                  \n                \n                \n                \n                \n                  \n                    \n                      \n                        \n                        第51回 阿賀野川ござれや花火\n                      \n                      \n                        \n                        \n                      \n                      \n                        \n                          超特大スターマインの花鳥風月をお見逃しなく\n                          新潟県・新潟市北区/阿賀野川松浜橋上流側\n                          期間：2025年8月25日(月)\n                            \n                              例年の人出：20万人\n                              行ってみたい：7\n                              行ってよかった：5\n                              \n                              有料席：あり\n                              \n                            \n                          \n                        \n                      \n                    \n                  \n                \n                \n\n\n\n\n\n\n                \n                \n                  \n                    \n                      \n                        \n                        おぢやまつり大花火大会2024\n                      \n                      \n                        \n                        \n                      \n                      \n                        \n                          超ワイド大スターマインが夜空に咲く\n                          新潟県・小千谷市/信濃川河川敷(旭橋下流)\n                          期間：2024年8月24日(土)おぢやまつりは8月23日(金)～25日(日)の3日間\n                            \n                              例年の人出：18万人\n                              行ってみたい：5\n                              行ってよかった：2\n                              \n                              有料席：あり\n                              \n                            \n                          \n                        \n                      \n                    \n                  \n                \n                \n                \n                \n                  \n                    \n                      \n                        \n                        ぎおん柏崎まつり 海の大花火大会\n                      \n                      \n                        \n                        \n                      \n                      \n                        \n                          尺玉100発一斉打上など豪華な花火がめじろ押し\n                          新潟県・柏崎市/柏崎市中央海岸・みなとまち海浜公園一帯\n                          期間：2025年7月26日(土)\n                            \n                              例年の人出：約17万人\n                              行ってみたい：24\n                              行ってよかった：18\n                              \n                              有料席：あり\n                              屋台：あり\n                            \n                          \n                        \n                      \n                    \n                  \n                \n                \n                \n                \n                  \n                    \n                      \n                        \n                        浅原神社 秋季例大祭奉納大煙火\n                      \n                      \n                        \n                        \n                      \n                      \n                        \n                          四尺玉をはじめ尺玉多数、大迫力の尺玉連発を堪能\n                          新潟県・小千谷市/片貝町浅原神社裏手\n                          期間：2025年9月12日(金)・13日(土)\n                            \n                              例年の人出：約17万人\n                              行ってみたい：15\n                              行ってよかった：11\n                              \n                              有料席：あり\n                              屋台：あり\n                            \n                          \n                        \n                      \n                    \n                  \n                \n                \n                \n                \n                  \n                    \n                      \n                        \n                        河口湖湖上祭\n                      \n                      \n                        \n                        \n                      \n                      \n                        \n                          河口湖の夜空を彩る大迫力の花火\n                          山梨県・南都留郡富士河口湖町/河口湖畔船津浜\n                          期間：2025年8月5日(火)\n                            \n                              例年の人出：12万人\n                              行ってみたい：24\n                              行ってよかった：8\n                              \n                              \n                              屋台：あり\n                            \n                          \n                        \n                      \n                    \n                  \n                \n                \n\n\n\n\n\n                \n                \n              \n              \n              \n  \n    規模の大きな主要花火大会\n  \n\n                            \n              \n              \n              \n                \n                  \n                  1\n                  \n                    \n                      \n                        \n                      \n                      2\n                      \n                    \n                      \n                      3\n                      \n                    \n                      \n                      4\n                      \n                    \n                      \n                      5\n                      \n                        \n                          …\n                        \n                      \n                    \n                  \n                  7\n                  \n                  \n                  次へ\n                  \n                \n              \n              \n              \n\n\n\n\n\n  \n\n\n\n\n\n\n\n\n\n  \n\n\n\n \n            \n\n            \n              \n              \n              \n                カレンダーから花火大会を探す【甲信越】\n                \n  \n  \n    \n      \n        \n          \n          今週末開催の花火大会\n        \n      \n    \n    \n      \n        \n          \n          来週末開催の花火大会\n        \n      \n    \n  \n  \n\n                \n                日付を選んで、その日に開催される花火大会をチェックしよう！\n                              \n              \n                \n                  \n                    \n                    \n                    \n                    7月\n                    \n                    8月\n                    \n                    9月\n                    \n                  \n                  \n                    \n                    \n                      7月開催の花火大会一覧はこちら\n                      \n                        \n                          \n                            月\n                            火\n                            水\n                            木\n                            金\n                            土\n                            日\n                          \n                          \n                          \n                            \n                            \n                            \n                            \n                            \n                            \n                            1\n                                \n                                  \n                                  \n                                  \n                                \n                              \n                            \n                            \n                            \n                            2\n                                \n                                  \n                                  \n                                  \n                                \n                              \n                            \n                            \n                            \n                            3\n                                \n                                  \n                                  \n                                  \n                                \n                              \n                            \n                            \n                            \n                            4\n                                \n                                  \n                                  \n                                  \n                                \n                              \n                            \n                            \n                            \n                            5\n                                \n                                  \n                                  \n                                  \n                                \n                              \n                            \n                            \n                            \n                            6\n                                \n                                  \n                                  \n                                  \n                                \n                              \n                            \n                            \n                          \n                          \n                          \n                            \n                            \n                            7\n                                \n                                  \n                                  \n                                  \n                                \n                              \n                            \n                            \n                            \n                            8\n                                \n                                  \n                                  \n                                  \n                                \n                              \n                            \n                            \n                            \n                            9\n                                \n                                  \n                                  \n                                  \n                                \n                              \n                            \n                            \n                            \n                            10\n                                \n                                  \n                                  \n                                  \n                                \n                              \n                            \n                            \n                            \n                            11\n                                \n                                  \n                                  \n                                  \n                                \n                              \n                            \n                            \n                            \n                            12\n                                \n                                  \n                                  \n                                  \n                                \n                              \n                            \n                            \n                            \n                            13\n                                \n                                  \n                                  \n                                  \n                                \n                              \n                            \n                            \n                          \n                          \n                          \n                            \n                            \n                            14\n                                \n                                  \n                                  \n                                  \n                                \n                              \n                            \n                            \n                            \n                            15\n                                \n                                  \n                                  \n                                  \n                                \n                              \n                            \n                            \n                            \n                            16\n                                \n                                  \n                                  \n                                  \n                                \n                              \n                            \n                            \n                            \n                            17\n                                \n                                  \n                                  \n                                  \n                                \n                              \n                            \n                            \n                            \n                            18\n                                \n                                  \n                                  \n                                  \n                                \n                              \n                            \n                            \n                            \n                            19\n                                \n                                  \n                                  \n                                  \n                                \n                              \n                            \n                            \n                            \n                            20\n                                \n                                  \n                                  \n                                  \n                                \n                              \n                            \n                            \n                          \n                          \n                          \n                            \n                            \n                            21\n                                \n                                  \n                                  \n                                  \n                                \n                              \n                            \n                            \n                            \n                            22\n                                \n                                  \n                                  \n                                  \n                                \n                              \n                            \n                            \n                            \n                            23\n                                \n                                  \n                                  \n                                  \n                                \n                              \n                            \n                            \n                            \n                            24\n                                \n                                  \n                                  \n                                  \n                                \n                              \n                            \n                            \n                            \n                            25\n                                \n                                  \n                                  \n                                  \n                                \n                              \n                            \n                            \n                            \n                            26\n                                \n                                  \n                                  \n                                  \n                                \n                              \n                            \n                            \n                            \n                            27\n                                \n                                  \n                                  \n                                  \n                                \n                              \n                            \n                            \n                          \n                          \n                          \n                            \n                            \n                            28\n                                \n                                  \n                                  \n                                  \n                                \n                              \n                            \n                            \n                            \n                            29\n                                \n                                  \n                                  \n                                  \n                                \n                              \n                            \n                            \n                            \n                            30\n                                \n                                  \n                                  \n                                  \n                                \n                              \n                            \n                            \n                            \n                            31\n                                \n                                  \n                                  \n                                  \n                                \n                              \n                            \n                            \n                            \n                            \n                            \n                            \n                            \n                            \n                            \n                            \n                            \n                            \n                            \n                            \n                          \n                          \n                        \n                      \n                    \n                    \n                    \n                    \n                      8月開催の花火大会一覧はこちら\n                      \n                        \n                          \n                            月\n                            火\n                            水\n                            木\n                            金\n                            土\n                            日\n                          \n                          \n                          \n                            \n                            \n                            \n                            \n                            \n                            \n                            \n                            \n                            \n                            \n                            \n                            \n                            \n                            \n                            \n                            \n                            \n                            \n                            1\n                                \n                                  \n                                  \n                                  \n                                \n                              \n                            \n                            \n                            \n                            2\n                                \n                                  \n                                  \n                                  \n                                \n                              \n                            \n                            \n                            \n                            3\n                                \n                                  \n                                  \n                                  \n                                \n                              \n                            \n                            \n                          \n                          \n                          \n                            \n                            \n                            4\n                                \n                                  \n                                  \n                                  \n                                \n                              \n                            \n                            \n                            \n                            5\n                                \n                                  \n                                  \n                                  \n                                \n                              \n                            \n                            \n                            \n                            6\n                                \n                                  \n                                  \n                                  \n                                \n                              \n                            \n                            \n                            \n                            7\n                                \n                                  \n                                  \n                                  \n                                \n                              \n                            \n                            \n                            \n                            8\n                                \n                                  \n                                  \n                                  \n                                \n                              \n                            \n                            \n                            \n                            9\n                                \n                                  \n                                  \n                                  \n                                \n                              \n                            \n                            \n                            \n                            10\n                                \n                                  \n                                  \n                                  \n                                \n                              \n                            \n                            \n                          \n                          \n                          \n                            \n                            \n                            11\n                                \n                                  \n                                  \n                                  \n                                \n                              \n                            \n                            \n                            \n                            12\n                                \n                                  \n                                  \n                                  \n                                \n                              \n                            \n                            \n                            \n                            13\n                                \n                                  \n                                  \n                                  \n                                \n                              \n                            \n                            \n                            \n                            14\n                                \n                                  \n                                  \n                                  \n                                \n                              \n                            \n                            \n                            \n                            15\n                                \n                                  \n                                  \n                                  \n                                \n                              \n                            \n                            \n                            \n                            16\n                                \n                                  \n                                  \n                                  \n                                \n                              \n                            \n                            \n                            \n                            17\n                                \n                                  \n                                  \n                                  \n                                \n                              \n                            \n                            \n                          \n                          \n                          \n                            \n                            \n                            18\n                                \n                                  \n                                  \n                                  \n                                \n                              \n                            \n                            \n                            \n                            19\n                                \n                                  \n                                  \n                                  \n                                \n                              \n                            \n                            \n                            \n                            20\n                                \n                                  \n                                  \n                                  \n                                \n                              \n                            \n                            \n                            \n                            21\n                                \n                                  \n                                  \n                                  \n                                \n                              \n                            \n                            \n                            \n                            22\n                                \n                                  \n                                  \n                                  \n                                \n                              \n                            \n                            \n                            \n                            23\n                                \n                                  \n                                  \n                                  \n                                \n                              \n                            \n                            \n                            \n                            24\n                                \n                                  \n                                  \n                                  \n                                \n                              \n                            \n                            \n                          \n                          \n                          \n                            \n                            \n                            25\n                                \n                                  \n                                  \n                                  \n                                \n                              \n                            \n                            \n                            \n                            26\n                                \n                                  \n                                  \n                                  \n                                \n                              \n                            \n                            \n                            \n                            27\n                                \n                                  \n                                  \n                                  \n                                \n                              \n                            \n                            \n                            \n                            28\n                                \n                                  \n                                  \n                                  \n                                \n                              \n                            \n                            \n                            \n                            29\n                                \n                                  \n                                  \n                                  \n                                \n                              \n                            \n                            \n                            \n                            30\n                                \n                                  \n                                  \n                                  \n                                \n                              \n                            \n                            \n                            \n                            31\n                                \n                                  \n                                  \n                                  \n                                \n                              \n                            \n                            \n                          \n                          \n                          \n                            \n                            \n                            \n                            \n                            \n                            \n                            \n                            \n                            \n                            \n                            \n                            \n                            \n                            \n                            \n                            \n                            \n                            \n                            \n                            \n                            \n                            \n                            \n                            \n                            \n                            \n                            \n                            \n                            \n                          \n                          \n                        \n                      \n                    \n                    \n                    \n                    \n                      9月開催の花火大会一覧はこちら\n                      \n                        \n                          \n                            月\n                            火\n                            水\n                            木\n                            金\n                            土\n                            日\n                          \n                          \n                          \n                            \n                            \n                            1\n                                \n                                  \n                                  \n                                  \n                                \n                              \n                            \n                            \n                            \n                            2\n                                \n                                  \n                                  \n                                  \n                                \n                              \n                            \n                            \n                            \n                            3\n                                \n                                  \n                                  \n                                  \n                                \n                              \n                            \n                            \n                            \n                            4\n                                \n                                  \n                                  \n                                  \n                                \n                              \n                            \n                            \n                            \n                            5\n                                \n                                  \n                                  \n                                  \n                                \n                              \n                            \n                            \n                            \n                            6\n                                \n                                  \n                                  \n                                  \n                                \n                              \n                            \n                            \n                            \n                            7\n                                \n                                  \n                                  \n                                  \n                                \n                              \n                            \n                            \n                          \n                          \n                          \n                            \n                            \n                            8\n                                \n                                  \n                                  \n                                  \n                                \n                              \n                            \n                            \n                            \n                            9\n                                \n                                  \n                                  \n                                  \n                                \n                              \n                            \n                            \n                            \n                            10\n                                \n                                  \n                                  \n                                  \n                                \n                              \n                            \n                            \n                            \n                            11\n                                \n                                  \n                                  \n                                  \n                                \n                              \n                            \n                            \n                            \n                            12\n                                \n                                  \n                                  \n                                  \n                                \n                              \n                            \n                            \n                            \n                            13\n                                \n                                  \n                                  \n                                  \n                                \n                              \n                            \n                            \n                            \n                            14\n                                \n                                  \n                                  \n                                  \n                                \n                              \n                            \n                            \n                          \n                          \n                          \n                            \n                            \n                            15\n                                \n                                  \n                                  \n                                  \n                                \n                              \n                            \n                            \n                            \n                            16\n                                \n                                  \n                                  \n                                  \n                                \n                              \n                            \n                            \n                            \n                            17\n                                \n                                  \n                                  \n                                  \n                                \n                              \n                            \n                            \n                            \n                            18\n                                \n                                  \n                                  \n                                  \n                                \n                              \n                            \n                            \n                            \n                            19\n                                \n                                  \n                                  \n                                  \n                                \n                              \n                            \n                            \n                            \n                            20\n                                \n                                  \n                                  \n                                  \n                                \n                              \n                            \n                            \n                            \n                            21\n                                \n                                  \n                                  \n                                  \n                                \n                              \n                            \n                            \n                          \n                          \n                          \n                            \n                            \n                            22\n                                \n                                  \n                                  \n                                  \n                                \n                              \n                            \n                            \n                            \n                            23\n                                \n                                  \n                                  \n                                  \n                                \n                              \n                            \n                            \n                            \n                            24\n                                \n                                  \n                                  \n                                  \n                                \n                              \n                            \n                            \n                            \n                            25\n                                \n                                  \n                                  \n                                  \n                                \n                              \n                            \n                            \n                            \n                            26\n                                \n                                  \n                                  \n                                  \n                                \n                              \n                            \n                            \n                            \n                            27\n                                \n                                  \n                                  \n                                  \n                                \n                              \n                            \n                            \n                            \n                            28\n                                \n                                  \n                                  \n                                  \n                                \n                              \n                            \n                            \n                          \n                          \n                          \n                            \n                            \n                            29\n                                \n                                  \n                                  \n                                  \n                                \n                              \n                            \n                            \n                            \n                            30\n                                \n                                  \n                                  \n                                  \n                                \n                              \n                            \n                            \n                            \n                            \n                            \n                            \n                            \n                            \n                            \n                            \n                            \n                            \n                            \n                            \n                            \n                            \n                            \n                            \n                            \n                            \n                            \n                            \n                          \n                          \n                        \n                      \n                    \n                    \n                    \n\n                    \n  \n    規模の大きな主要花火大会\n  \n\n                  \n                  \n                  \n                \n              \n              \n              \n                          \n              \n                花火トピックス\n                全国の花火大会の開催・中止情報をお届け！注目の花火大会や、知って得する花火ネタをご紹介。\n              \n              \n                \n                  \n                  \n                      \n                      2025年も「金麦」“夏の味”の発売スタート！ほかの季節の金麦となにが違う？四季の味へのこだわりを聞いてみた\n                      \n                        PR\n                      \n                      全国\n                      \n                        2025年6月12日 10:00 更新\n                        \n                      \n                    \n                  \n                  \n                      \n                      「金麦」“夏の味”を編集部員が体験！ 「おうちで金麦花火セット」が当たるスペシャルなキャンペーンも紹介\n                      \n                        PR\n                      \n                      全国\n                      \n                        2025年6月12日 10:00 更新\n                        \n                      \n                    \n                  \n                  \n                      \n                      「日本三大花火大会」とは？日本最大規模の超大型花火大会をチェック！\n                      \n                        \n                      \n                      全国\n                      \n                        2025年6月11日 14:30 更新\n                        \n                      \n                    \n                  \n                \n              \n              \n                花火トピックスをもっと見る\n              \n            \n              \n                          \n              甲信越の花火大会を探す\n              \n                \n                  周辺のエリア・都道府県から探す\n                \n                \n                  \n                  山梨県\n                  \n                  長野県\n                  \n                  新潟県\n                  \n                \n\n                \n                \n                  開催状況から花火大会を探す\n                  \n                    開催予定の花火大会\n                    \n                  \n                \n                \n\n                花火カレンダーから探す\n                  \n\n                  \n                    \n                      \n                        \n                          甲信越の花火カレンダー\n                        \n                      \n                      \n                        \n                          今日開催の花火大会\n                        \n                      \n                      \n                        \n                          明日開催の花火大会\n                        \n                      \n                    \n                  \n\n                  開催される月から探す\n                    \n\n                    \n                        6月\n                      \n                        7月\n                      \n                        8月\n                      \n                        9月\n                      \n                        10月\n                      \n                        11月\n                      \n\n                ランキングから探す\n                \n                  \n                    \n                      \n                        甲信越の人気花火大会ランキング\n                      \n                      \n                        甲信越の行ってみたい花火大会ランキング\n                      \n                    \n                    \n                      \n                        甲信越の行ってよかった花火大会ランキング\n                      \n                      \n                        甲信越の打ち上げ数ランキング\n                      \n                    \n                    \n                      \n                        甲信越の人出ランキング\n                      \n                    \n                  \n                \n              \n            \n              \n                          \n              都道府県から花火大会を探す\n              \n                \n                  北海道\n                  北海道\n                \n                \n                  東　北\n                  宮城県\n                  青森県\n                  岩手県\n                  秋田県\n                  山形県\n                  福島県\n                \n                \n                  関　東\n                  東京都\n                  神奈川県\n                  千葉県\n                  埼玉県\n                  群馬県\n                  栃木県\n                  茨城県\n                \n                \n                  甲信越\n                  山梨県\n                  長野県\n                  新潟県\n                \n                \n                  北　陸\n                  石川県\n                  富山県\n                  福井県\n                \n                \n                  東　海\n                  愛知県\n                  岐阜県\n                  三重県\n                  静岡県\n                \n                \n                  関　西\n                  大阪府\n                  京都府\n                  兵庫県\n                  奈良県\n                  和歌山県\n                  滋賀県\n                \n                \n                  中　国\n                  広島県\n                  岡山県\n                  山口県\n                  鳥取県\n                  島根県\n                \n                \n                  四　国\n                  香川県\n                  愛媛県\n                  徳島県\n                  高知県\n                \n                \n                  九州・沖縄\n                  福岡県\n                  佐賀県\n                  長崎県\n                  熊本県\n                  大分県\n                  宮崎県\n                  鹿児島県\n                  沖縄県\n                \n              \n            \n              \n                       \n              花火特集2025\n              \n                花火大会をエリアから探す\n                \n                  北海道\n                  東北\n                  関東\n                  甲信越\n                  北陸\n                  東海\n                  関西\n                  中国\n                  四国\n                  九州・沖縄\n                \n\n                花火大会人気ランキング\n                \n                  全国\n                  北海道\n                  東北\n                  関東\n                  甲信越\n                  北陸\n                  東海\n                  関西\n                  中国\n                  四国\n                  九州・沖縄\n                \n                \n                \n                  打ち上げ数ランキング\n                  人出ランキング \n                  行ってみたいランキング\n                  行ってよかったランキング \n                \n                \n                \n                \n                \n                  花火大会カレンダー\n                  5月開催の花火大会\n                   6月開催の花火大会\n                    7月開催の花火大会\n                  8月開催の花火大会           \n                  9月開催の花火大会\n                  10月開催の花火大会\n                            \n                \n                \n               \n                  今日開催の花火大会\n                  明日開催の花火大会                  \n                 \n                \n                \n                  有料席のチケット情報\n                \n                \n                \n                  花火トピックス\n                \n                \n\n              \n            \n            \n            \n          \n          \n            \n\n\n\n\n\n\n\n\n            \n  おすすめ情報\n  \n\n\n\n\n\n\n\n\n\n\n\n\n\n\n\n\n\n\n\n\n\n\n  \n\n\n            \n            \n              人気花火大会ランキング【甲信越】\n                \n                  2025年6月14日 更新\n                  \n                    \n                        1\n                        第41回 咲花温泉水中花火大会\n                      \n                    \n                        2\n                        まき夏まつり 花火大会\n                      \n                    \n                        3\n                        河口湖湖上祭\n                      \n                    \n                        4\n                        長岡まつり大花火大会\n                      \n                    \n                        5\n                        長岡花火ローズファンタジー\n                      \n                  \n                  もっと見る \n                \n            \n            \n            \n              \n  閲覧履歴\n  \n    \n      \n        最近見た花火大会のページはありません。\n      \n    \n    閲覧履歴をもっと見る \n  \n\n            \n            \n  おすすめ記事\n  \n    \n      \n        \n          \n            \n            甲信越で今週末開催されるおすすめ花火大会\n          \n        \n      \n      \n    \n  \n\n                      \n            花火をもっと楽しむ\n            \n              \n\n                \n                  \n                  \n                    開催予定の花火大会\n                    2025年に開催予定の花火大会をご紹介\n                  \n                  \n                \n                  \n                  \n                    花火大会人気ランキング\n                    毎日更新！アクセス数の多い人気花火大会をエリア別にランキング\n                  \n                    \n                   \n                  \n                  \n                    有料席のチケット情報\n                    間近で上がる迫力満点の花火を座ってゆったり楽しもう！！\n                  \n                                         \n                  \n                  \n                  \n                    宿泊付き花火鑑賞ツアー販売中\n                    有料席とホテルをセットにしたウォーカー限定ツアーを販売中！！\n                  \n                   \n                                                   \n                  \n                   \n                  \n                  \n                    屋台のある花火大会をご紹介\n                    花火大会を盛り上げる屋台グルメを楽しめる人気の花火大会10選！\n                  \n                   \n                     \n                 \n                \n                  \n                  \n                    花火カレンダー\n                    花火大会の開催スケジュールをカレンダーでチェック！\n                  \n                  \n      \n                 \n                \n                \n\n                \n                  \n                  \n                    おでかけトピックス\n                    全国の花火大会の開催・中止情報をお届け！新しい花火の楽しみ方もご紹介。\n                  \n                  \n                \n              \n                \n\n                \n                \n\n              \n            \n           \n                      \n          \n            \n\n\n\n\n\n\n\n\n          \n          \n        \n      \n    \n            \n          \n          \n            \n              \n              花火大会2025\n            \n            \n          \n          \n          \n            \n              \n              全国の花火大会の人出ランキング\n            \n            \n          \n          \n          \n            \n              \n              甲信越の花火大会の人出ランキング\n            \n            \n          \n          \n        \n    \n  \n  \n    \n  \n    ウォーカープラス・季節特集\n    \n      ウォーカープラス\n      いちご狩り\n      お花見\n      ゴールデンウィーク\n      花火大会\n      夏休み（夏祭り）\n      紅葉\n      イルミネーション\n    \n    関連サイト\n    \n      レタスクラブ\n      ダ・ヴィンチWeb\n      WEBザテレビジョン\n      MOVIE WALKER PRESS\n      毎日が発見ネット\n      PressWalker\n      \n    \n  \n  \n    \n      \n        利用規約\n        プライバシーポリシー\n        推奨環境\n        お問い合わせ\n        プレスリリース・情報提供\n        媒体資料\n        広告掲載について\n        会社概要\n        利用者情報の外部送信について\n      \n    \n    \n      \n      © KADOKAWA CORPORATION\n    \n  \n\n  \n  \n\n\n\n\n\n\n\n\n\n  \n  \n  \n  \n  \n  \n  \n  \n  \n    {\n      lang: 'ja'\n    }\n  \n\n\n(function(a,e,b,f,g,c,d){a[b]=a[b]||function(){(a[b].q=a[b].q||[]).push(arguments)};c=e.createElement(f);c.async=1;c.src=\"https://www.clarity.ms/tag/\"+g;d=e.getElementsByTagName(f)[0];d.parentNode.insertBefore(c,d)})(window,document,\"clarity\",\"script\",\"f13adjk1bm\");"
      },
      {
        "title": "<iframe src=\"//www.googletagmanager.com/ns.html?id=GTM-MFFS32\"",
        "date": "2025年6月14日",
        "location": "新潟県・長岡市/信濃川河川敷",
        "visitors": "40万人",
        "fireworks": "2万発",
        "rawText": "<iframe src=\"//www.googletagmanager.com/ns.html?id=GTM-MFFS32\"\n        height=\"0\" width=\"0\" style=\"display:none;visibility:hidden\"></iframe>\n(function(w,d,s,l,i){w[l]=w[l]||[];w[l].push({'gtm.start':\n    new Date().getTime(),event:'gtm.js'});var f=d.getElementsByTagName(s)[0],\nj=d.createElement(s),dl=l!='dataLayer'?'&l='+l:'';j.async=true;j.src=\n'//www.googletagmanager.com/gtm.js?id='+i+dl;f.parentNode.insertBefore(j,f);\n})(window,document,'script','dataLayer','GTM-MFFS32');\n\n  \n  \n    \n      \n      \n        \n  \n    \n      \n.plus {fill:url(#gradient);}.font {fill: #fff; }\n            \n            \n          \n\n\n\n\n\n\n\n\n\n\n\n\n\n\n\n\n\n\n\n\n\n\n\n\n\n\n\n\n\n\n\n\n\n      \n    \n    \n      \n      \n    \n    \n  \n\n\n        \n\n\n\n全国約900大会の花火大会情報をお届け！\n\n \n\n\n \n    \n    \n    \n    \n\n                  \n            \n              \n                \n                  花火特集2025\n                  北海道\n                  東北\n                  関東\n                    \n                      東京\n                      神奈川\n                      千葉\n                    \n                  \n                  甲信越\n                  北陸\n                  東海\n                  \n                      愛知\n                    \n                   \n                  関西\n                    \n                      大阪\n                    \n                  \n                  中国\n                  四国\n                  九州・沖縄\n                \n              \n                         \n                \n                エリアから探す\n                \n                人気ランキング\n           \t\t\n                開催予定の花火大会\n                花火カレンダー\n                \n                おうちで金麦\n                \n              \n              \n\n    \t\t\t\n\n\n\n  \n  \n    \n      \n\n\n\n\t\n    \n    \n      \n\n\n\n    \n    \n  \n\n\n\n            \n          \n        \n\n\n\n\n\n\n\n\n\n        \n   2025年の情報に順次更新しておりますが、過去の情報もございます。当日の開催情報は大会主催者に確認ください \n\n\n\n                \n          \n          \n            \n              \n              花火大会2025\n            \n            \n          \n          \n          \n            \n              \n              全国の花火大会の人出ランキング\n            \n            \n          \n          \n          \n            \n              \n              甲信越の花火大会の人出ランキング\n            \n            \n          \n          \n        \n     \n      \n    \n    \n      \n        \n          \n              \n\n            \n            \n              \n                甲信越の花火大会の人出ランキング\n                例年の来場者数をもとにランキング！混雑を予測しておでかけの参考にしよう！\n              \n              \n              \n    \n        注目の花火大会\n        \n          河口湖湖上祭長岡まつり大花火大会\n        \n    \n\n              2025年6月14日 更新\n              エリアを絞り込む\n              \n                \n                \n                甲信越\n                \n                山梨県\n                \n                \n                長野県\n                \n                \n                新潟県\n                \n              \n              その他のランキングから探す\n              \n                \n                  \n                    人気花火大会ランキング\n                    \n                        打ち上げ数ランキング\n                      \n                  \n                  \n                    \n                        行ってみたいランキング\n                      \n                    \n                        行ってよかったランキング\n                      \n                  \n                \n              \n\n              \n              \n                \n                \n                  \n                    \n                      \n                        \n                        第119回 長野えびす講煙火大会\n                      \n                      \n                        \n                        \n                      \n                      \n                        \n                          信州の澄んだ夜空を彩る晩秋の花火\n                          長野県・長野市/長野大橋西側  犀川第2緑地\n                          期間：2025年11月23日(日)\n                            \n                              例年の人出：約40万人\n                              行ってみたい：23\n                              行ってよかった：11\n                              \n                              有料席：あり\n                              屋台：あり\n                            \n                          \n                        \n                      \n                    \n                  \n                \n                \n                \n                \n                  \n                    \n                      \n                        \n                        長岡まつり大花火大会\n                      \n                      \n                        \n                        \n                      \n                      \n                        \n                          復興祈願花火フェニックスは、ほかにはない大迫力\n                          新潟県・長岡市/信濃川河川敷\n                          期間：2025年8月2日(土)・3日(日)\n                            \n                              例年の人出：約34万5000人\n                              行ってみたい：81\n                              行ってよかった：42\n                              \n                              有料席：あり\n                              屋台：あり\n                            \n                          \n                        \n                      \n                    \n                  \n                \n                \n                \n                \n                  \n                    \n                      \n                        \n                        新潟まつり花火大会\n                      \n                      \n                        \n                        \n                      \n                      \n                        \n                          日本一の大河「信濃川」を舞台に繰り広げられる壮大な花火大会\n                          新潟県・新潟市中央区/新潟市中央区信濃川河畔(昭和大橋周辺)\n                          期間：2025年8月10日(日)\n                            \n                              例年の人出：約32万人\n                              行ってみたい：20\n                              行ってよかった：7\n                              \n                              \n                              \n                            \n                          \n                        \n                      \n                    \n                  \n                \n                \n\n\n\n\n\n                \n                \n                  \n                    \n                      \n                        \n                        全国新作花火チャレンジカップ2025\n                      \n                      \n                        \n                        \n                      \n                      \n                        \n                          6年ぶりにリニューアルし、分散方式による競技花火を開催決定\n                          長野県・諏訪市/長野県諏訪市湖畔公園前諏訪湖上\n                          期間：予選：2025年9月6日(土)・13日(土)・20日(土)・27日(土)。決勝：10月26日(日)\n                            \n                              例年の人出：約25万人\n                              行ってみたい：7\n                              行ってよかった：2\n                              \n                              \n                              \n                            \n                          \n                        \n                      \n                    \n                  \n                \n                \n                \n                \n                  \n                    \n                      \n                        \n                        市川三郷町ふるさと夏まつり　第37回「神明の花火大会」\n                      \n                      \n                        \n                        \n                      \n                      \n                        \n                          音楽と彩る約2万発の夜空の芸術\n                          山梨県・西八代郡市川三郷町/三郡橋下流笛吹川河畔\n                          期間：2025年8月7日(木)\n                            \n                              例年の人出：約20万人\n                              行ってみたい：28\n                              行ってよかった：20\n                              \n                              有料席：あり\n                              屋台：あり\n                            \n                          \n                        \n                      \n                    \n                  \n                \n                \n                \n                \n                  \n                    \n                      \n                        \n                        第51回 阿賀野川ござれや花火\n                      \n                      \n                        \n                        \n                      \n                      \n                        \n                          超特大スターマインの花鳥風月をお見逃しなく\n                          新潟県・新潟市北区/阿賀野川松浜橋上流側\n                          期間：2025年8月25日(月)\n                            \n                              例年の人出：20万人\n                              行ってみたい：7\n                              行ってよかった：5\n                              \n                              有料席：あり\n                              \n                            \n                          \n                        \n                      \n                    \n                  \n                \n                \n\n\n\n\n\n\n                \n                \n                  \n                    \n                      \n                        \n                        おぢやまつり大花火大会2024\n                      \n                      \n                        \n                        \n                      \n                      \n                        \n                          超ワイド大スターマインが夜空に咲く\n                          新潟県・小千谷市/信濃川河川敷(旭橋下流)\n                          期間：2024年8月24日(土)おぢやまつりは8月23日(金)～25日(日)の3日間\n                            \n                              例年の人出：18万人\n                              行ってみたい：5\n                              行ってよかった：2\n                              \n                              有料席：あり\n                              \n                            \n                          \n                        \n                      \n                    \n                  \n                \n                \n                \n                \n                  \n                    \n                      \n                        \n                        ぎおん柏崎まつり 海の大花火大会\n                      \n                      \n                        \n                        \n                      \n                      \n                        \n                          尺玉100発一斉打上など豪華な花火がめじろ押し\n                          新潟県・柏崎市/柏崎市中央海岸・みなとまち海浜公園一帯\n                          期間：2025年7月26日(土)\n                            \n                              例年の人出：約17万人\n                              行ってみたい：24\n                              行ってよかった：18\n                              \n                              有料席：あり\n                              屋台：あり\n                            \n                          \n                        \n                      \n                    \n                  \n                \n                \n                \n                \n                  \n                    \n                      \n                        \n                        浅原神社 秋季例大祭奉納大煙火\n                      \n                      \n                        \n                        \n                      \n                      \n                        \n                          四尺玉をはじめ尺玉多数、大迫力の尺玉連発を堪能\n                          新潟県・小千谷市/片貝町浅原神社裏手\n                          期間：2025年9月12日(金)・13日(土)\n                            \n                              例年の人出：約17万人\n                              行ってみたい：15\n                              行ってよかった：11\n                              \n                              有料席：あり\n                              屋台：あり\n                            \n                          \n                        \n                      \n                    \n                  \n                \n                \n                \n                \n                  \n                    \n                      \n                        \n                        河口湖湖上祭\n                      \n                      \n                        \n                        \n                      \n                      \n                        \n                          河口湖の夜空を彩る大迫力の花火\n                          山梨県・南都留郡富士河口湖町/河口湖畔船津浜\n                          期間：2025年8月5日(火)\n                            \n                              例年の人出：12万人\n                              行ってみたい：24\n                              行ってよかった：8\n                              \n                              \n                              屋台：あり\n                            \n                          \n                        \n                      \n                    \n                  \n                \n                \n\n\n\n\n\n                \n                \n              \n              \n              \n  \n    規模の大きな主要花火大会\n  \n\n                            \n              \n              \n              \n                \n                  \n                  1\n                  \n                    \n                      \n                        \n                      \n                      2\n                      \n                    \n                      \n                      3\n                      \n                    \n                      \n                      4\n                      \n                    \n                      \n                      5\n                      \n                        \n                          …\n                        \n                      \n                    \n                  \n                  7\n                  \n                  \n                  次へ\n                  \n                \n              \n              \n              \n\n\n\n\n\n  \n\n\n\n\n\n\n\n\n\n  \n\n\n\n \n            \n\n            \n              \n              \n              \n                カレンダーから花火大会を探す【甲信越】\n                \n  \n  \n    \n      \n        \n          \n          今週末開催の花火大会\n        \n      \n    \n    \n      \n        \n          \n          来週末開催の花火大会\n        \n      \n    \n  \n  \n\n                \n                日付を選んで、その日に開催される花火大会をチェックしよう！\n                              \n              \n                \n                  \n                    \n                    \n                    \n                    7月\n                    \n                    8月\n                    \n                    9月\n                    \n                  \n                  \n                    \n                    \n                      7月開催の花火大会一覧はこちら\n                      \n                        \n                          \n                            月\n                            火\n                            水\n                            木\n                            金\n                            土\n                            日\n                          \n                          \n                          \n                            \n                            \n                            \n                            \n                            \n                            \n                            1\n                                \n                                  \n                                  \n                                  \n                                \n                              \n                            \n                            \n                            \n                            2\n                                \n                                  \n                                  \n                                  \n                                \n                              \n                            \n                            \n                            \n                            3\n                                \n                                  \n                                  \n                                  \n                                \n                              \n                            \n                            \n                            \n                            4\n                                \n                                  \n                                  \n                                  \n                                \n                              \n                            \n                            \n                            \n                            5\n                                \n                                  \n                                  \n                                  \n                                \n                              \n                            \n                            \n                            \n                            6\n                                \n                                  \n                                  \n                                  \n                                \n                              \n                            \n                            \n                          \n                          \n                          \n                            \n                            \n                            7\n                                \n                                  \n                                  \n                                  \n                                \n                              \n                            \n                            \n                            \n                            8\n                                \n                                  \n                                  \n                                  \n                                \n                              \n                            \n                            \n                            \n                            9\n                                \n                                  \n                                  \n                                  \n                                \n                              \n                            \n                            \n                            \n                            10\n                                \n                                  \n                                  \n                                  \n                                \n                              \n                            \n                            \n                            \n                            11\n                                \n                                  \n                                  \n                                  \n                                \n                              \n                            \n                            \n                            \n                            12\n                                \n                                  \n                                  \n                                  \n                                \n                              \n                            \n                            \n                            \n                            13\n                                \n                                  \n                                  \n                                  \n                                \n                              \n                            \n                            \n                          \n                          \n                          \n                            \n                            \n                            14\n                                \n                                  \n                                  \n                                  \n                                \n                              \n                            \n                            \n                            \n                            15\n                                \n                                  \n                                  \n                                  \n                                \n                              \n                            \n                            \n                            \n                            16\n                                \n                                  \n                                  \n                                  \n                                \n                              \n                            \n                            \n                            \n                            17\n                                \n                                  \n                                  \n                                  \n                                \n                              \n                            \n                            \n                            \n                            18\n                                \n                                  \n                                  \n                                  \n                                \n                              \n                            \n                            \n                            \n                            19\n                                \n                                  \n                                  \n                                  \n                                \n                              \n                            \n                            \n                            \n                            20\n                                \n                                  \n                                  \n                                  \n                                \n                              \n                            \n                            \n                          \n                          \n                          \n                            \n                            \n                            21\n                                \n                                  \n                                  \n                                  \n                                \n                              \n                            \n                            \n                            \n                            22\n                                \n                                  \n                                  \n                                  \n                                \n                              \n                            \n                            \n                            \n                            23\n                                \n                                  \n                                  \n                                  \n                                \n                              \n                            \n                            \n                            \n                            24\n                                \n                                  \n                                  \n                                  \n                                \n                              \n                            \n                            \n                            \n                            25\n                                \n                                  \n                                  \n                                  \n                                \n                              \n                            \n                            \n                            \n                            26\n                                \n                                  \n                                  \n                                  \n                                \n                              \n                            \n                            \n                            \n                            27\n                                \n                                  \n                                  \n                                  \n                                \n                              \n                            \n                            \n                          \n                          \n                          \n                            \n                            \n                            28\n                                \n                                  \n                                  \n                                  \n                                \n                              \n                            \n                            \n                            \n                            29\n                                \n                                  \n                                  \n                                  \n                                \n                              \n                            \n                            \n                            \n                            30\n                                \n                                  \n                                  \n                                  \n                                \n                              \n                            \n                            \n                            \n                            31\n                                \n                                  \n                                  \n                                  \n                                \n                              \n                            \n                            \n                            \n                            \n                            \n                            \n                            \n                            \n                            \n                            \n                            \n                            \n                            \n                            \n                          \n                          \n                        \n                      \n                    \n                    \n                    \n                    \n                      8月開催の花火大会一覧はこちら\n                      \n                        \n                          \n                            月\n                            火\n                            水\n                            木\n                            金\n                            土\n                            日\n                          \n                          \n                          \n                            \n                            \n                            \n                            \n                            \n                            \n                            \n                            \n                            \n                            \n                            \n                            \n                            \n                            \n                            \n                            \n                            \n                            \n                            1\n                                \n                                  \n                                  \n                                  \n                                \n                              \n                            \n                            \n                            \n                            2\n                                \n                                  \n                                  \n                                  \n                                \n                              \n                            \n                            \n                            \n                            3\n                                \n                                  \n                                  \n                                  \n                                \n                              \n                            \n                            \n                          \n                          \n                          \n                            \n                            \n                            4\n                                \n                                  \n                                  \n                                  \n                                \n                              \n                            \n                            \n                            \n                            5\n                                \n                                  \n                                  \n                                  \n                                \n                              \n                            \n                            \n                            \n                            6\n                                \n                                  \n                                  \n                                  \n                                \n                              \n                            \n                            \n                            \n                            7\n                                \n                                  \n                                  \n                                  \n                                \n                              \n                            \n                            \n                            \n                            8\n                                \n                                  \n                                  \n                                  \n                                \n                              \n                            \n                            \n                            \n                            9\n                                \n                                  \n                                  \n                                  \n                                \n                              \n                            \n                            \n                            \n                            10\n                                \n                                  \n                                  \n                                  \n                                \n                              \n                            \n                            \n                          \n                          \n                          \n                            \n                            \n                            11\n                                \n                                  \n                                  \n                                  \n                                \n                              \n                            \n                            \n                            \n                            12\n                                \n                                  \n                                  \n                                  \n                                \n                              \n                            \n                            \n                            \n                            13\n                                \n                                  \n                                  \n                                  \n                                \n                              \n                            \n                            \n                            \n                            14\n                                \n                                  \n                                  \n                                  \n                                \n                              \n                            \n                            \n                            \n                            15\n                                \n                                  \n                                  \n                                  \n                                \n                              \n                            \n                            \n                            \n                            16\n                                \n                                  \n                                  \n                                  \n                                \n                              \n                            \n                            \n                            \n                            17\n                                \n                                  \n                                  \n                                  \n                                \n                              \n                            \n                            \n                          \n                          \n                          \n                            \n                            \n                            18\n                                \n                                  \n                                  \n                                  \n                                \n                              \n                            \n                            \n                            \n                            19\n                                \n                                  \n                                  \n                                  \n                                \n                              \n                            \n                            \n                            \n                            20\n                                \n                                  \n                                  \n                                  \n                                \n                              \n                            \n                            \n                            \n                            21\n                                \n                                  \n                                  \n                                  \n                                \n                              \n                            \n                            \n                            \n                            22\n                                \n                                  \n                                  \n                                  \n                                \n                              \n                            \n                            \n                            \n                            23\n                                \n                                  \n                                  \n                                  \n                                \n                              \n                            \n                            \n                            \n                            24\n                                \n                                  \n                                  \n                                  \n                                \n                              \n                            \n                            \n                          \n                          \n                          \n                            \n                            \n                            25\n                                \n                                  \n                                  \n                                  \n                                \n                              \n                            \n                            \n                            \n                            26\n                                \n                                  \n                                  \n                                  \n                                \n                              \n                            \n                            \n                            \n                            27\n                                \n                                  \n                                  \n                                  \n                                \n                              \n                            \n                            \n                            \n                            28\n                                \n                                  \n                                  \n                                  \n                                \n                              \n                            \n                            \n                            \n                            29\n                                \n                                  \n                                  \n                                  \n                                \n                              \n                            \n                            \n                            \n                            30\n                                \n                                  \n                                  \n                                  \n                                \n                              \n                            \n                            \n                            \n                            31\n                                \n                                  \n                                  \n                                  \n                                \n                              \n                            \n                            \n                          \n                          \n                          \n                            \n                            \n                            \n                            \n                            \n                            \n                            \n                            \n                            \n                            \n                            \n                            \n                            \n                            \n                            \n                            \n                            \n                            \n                            \n                            \n                            \n                            \n                            \n                            \n                            \n                            \n                            \n                            \n                            \n                          \n                          \n                        \n                      \n                    \n                    \n                    \n                    \n                      9月開催の花火大会一覧はこちら\n                      \n                        \n                          \n                            月\n                            火\n                            水\n                            木\n                            金\n                            土\n                            日\n                          \n                          \n                          \n                            \n                            \n                            1\n                                \n                                  \n                                  \n                                  \n                                \n                              \n                            \n                            \n                            \n                            2\n                                \n                                  \n                                  \n                                  \n                                \n                              \n                            \n                            \n                            \n                            3\n                                \n                                  \n                                  \n                                  \n                                \n                              \n                            \n                            \n                            \n                            4\n                                \n                                  \n                                  \n                                  \n                                \n                              \n                            \n                            \n                            \n                            5\n                                \n                                  \n                                  \n                                  \n                                \n                              \n                            \n                            \n                            \n                            6\n                                \n                                  \n                                  \n                                  \n                                \n                              \n                            \n                            \n                            \n                            7\n                                \n                                  \n                                  \n                                  \n                                \n                              \n                            \n                            \n                          \n                          \n                          \n                            \n                            \n                            8\n                                \n                                  \n                                  \n                                  \n                                \n                              \n                            \n                            \n                            \n                            9\n                                \n                                  \n                                  \n                                  \n                                \n                              \n                            \n                            \n                            \n                            10\n                                \n                                  \n                                  \n                                  \n                                \n                              \n                            \n                            \n                            \n                            11\n                                \n                                  \n                                  \n                                  \n                                \n                              \n                            \n                            \n                            \n                            12\n                                \n                                  \n                                  \n                                  \n                                \n                              \n                            \n                            \n                            \n                            13\n                                \n                                  \n                                  \n                                  \n                                \n                              \n                            \n                            \n                            \n                            14\n                                \n                                  \n                                  \n                                  \n                                \n                              \n                            \n                            \n                          \n                          \n                          \n                            \n                            \n                            15\n                                \n                                  \n                                  \n                                  \n                                \n                              \n                            \n                            \n                            \n                            16\n                                \n                                  \n                                  \n                                  \n                                \n                              \n                            \n                            \n                            \n                            17\n                                \n                                  \n                                  \n                                  \n                                \n                              \n                            \n                            \n                            \n                            18\n                                \n                                  \n                                  \n                                  \n                                \n                              \n                            \n                            \n                            \n                            19\n                                \n                                  \n                                  \n                                  \n                                \n                              \n                            \n                            \n                            \n                            20\n                                \n                                  \n                                  \n                                  \n                                \n                              \n                            \n                            \n                            \n                            21\n                                \n                                  \n                                  \n                                  \n                                \n                              \n                            \n                            \n                          \n                          \n                          \n                            \n                            \n                            22\n                                \n                                  \n                                  \n                                  \n                                \n                              \n                            \n                            \n                            \n                            23\n                                \n                                  \n                                  \n                                  \n                                \n                              \n                            \n                            \n                            \n                            24\n                                \n                                  \n                                  \n                                  \n                                \n                              \n                            \n                            \n                            \n                            25\n                                \n                                  \n                                  \n                                  \n                                \n                              \n                            \n                            \n                            \n                            26\n                                \n                                  \n                                  \n                                  \n                                \n                              \n                            \n                            \n                            \n                            27\n                                \n                                  \n                                  \n                                  \n                                \n                              \n                            \n                            \n                            \n                            28\n                                \n                                  \n                                  \n                                  \n                                \n                              \n                            \n                            \n                          \n                          \n                          \n                            \n                            \n                            29\n                                \n                                  \n                                  \n                                  \n                                \n                              \n                            \n                            \n                            \n                            30\n                                \n                                  \n                                  \n                                  \n                                \n                              \n                            \n                            \n                            \n                            \n                            \n                            \n                            \n                            \n                            \n                            \n                            \n                            \n                            \n                            \n                            \n                            \n                            \n                            \n                            \n                            \n                            \n                            \n                          \n                          \n                        \n                      \n                    \n                    \n                    \n\n                    \n  \n    規模の大きな主要花火大会\n  \n\n                  \n                  \n                  \n                \n              \n              \n              \n                          \n              \n                花火トピックス\n                全国の花火大会の開催・中止情報をお届け！注目の花火大会や、知って得する花火ネタをご紹介。\n              \n              \n                \n                  \n                  \n                      \n                      2025年も「金麦」“夏の味”の発売スタート！ほかの季節の金麦となにが違う？四季の味へのこだわりを聞いてみた\n                      \n                        PR\n                      \n                      全国\n                      \n                        2025年6月12日 10:00 更新\n                        \n                      \n                    \n                  \n                  \n                      \n                      「金麦」“夏の味”を編集部員が体験！ 「おうちで金麦花火セット」が当たるスペシャルなキャンペーンも紹介\n                      \n                        PR\n                      \n                      全国\n                      \n                        2025年6月12日 10:00 更新\n                        \n                      \n                    \n                  \n                  \n                      \n                      「日本三大花火大会」とは？日本最大規模の超大型花火大会をチェック！\n                      \n                        \n                      \n                      全国\n                      \n                        2025年6月11日 14:30 更新\n                        \n                      \n                    \n                  \n                \n              \n              \n                花火トピックスをもっと見る\n              \n            \n              \n                          \n              甲信越の花火大会を探す\n              \n                \n                  周辺のエリア・都道府県から探す\n                \n                \n                  \n                  山梨県\n                  \n                  長野県\n                  \n                  新潟県\n                  \n                \n\n                \n                \n                  開催状況から花火大会を探す\n                  \n                    開催予定の花火大会\n                    \n                  \n                \n                \n\n                花火カレンダーから探す\n                  \n\n                  \n                    \n                      \n                        \n                          甲信越の花火カレンダー\n                        \n                      \n                      \n                        \n                          今日開催の花火大会\n                        \n                      \n                      \n                        \n                          明日開催の花火大会\n                        \n                      \n                    \n                  \n\n                  開催される月から探す\n                    \n\n                    \n                        6月\n                      \n                        7月\n                      \n                        8月\n                      \n                        9月\n                      \n                        10月\n                      \n                        11月\n                      \n\n                ランキングから探す\n                \n                  \n                    \n                      \n                        甲信越の人気花火大会ランキング\n                      \n                      \n                        甲信越の行ってみたい花火大会ランキング\n                      \n                    \n                    \n                      \n                        甲信越の行ってよかった花火大会ランキング\n                      \n                      \n                        甲信越の打ち上げ数ランキング\n                      \n                    \n                    \n                      \n                        甲信越の人出ランキング\n                      \n                    \n                  \n                \n              \n            \n              \n                          \n              都道府県から花火大会を探す\n              \n                \n                  北海道\n                  北海道\n                \n                \n                  東　北\n                  宮城県\n                  青森県\n                  岩手県\n                  秋田県\n                  山形県\n                  福島県\n                \n                \n                  関　東\n                  東京都\n                  神奈川県\n                  千葉県\n                  埼玉県\n                  群馬県\n                  栃木県\n                  茨城県\n                \n                \n                  甲信越\n                  山梨県\n                  長野県\n                  新潟県\n                \n                \n                  北　陸\n                  石川県\n                  富山県\n                  福井県\n                \n                \n                  東　海\n                  愛知県\n                  岐阜県\n                  三重県\n                  静岡県\n                \n                \n                  関　西\n                  大阪府\n                  京都府\n                  兵庫県\n                  奈良県\n                  和歌山県\n                  滋賀県\n                \n                \n                  中　国\n                  広島県\n                  岡山県\n                  山口県\n                  鳥取県\n                  島根県\n                \n                \n                  四　国\n                  香川県\n                  愛媛県\n                  徳島県\n                  高知県\n                \n                \n                  九州・沖縄\n                  福岡県\n                  佐賀県\n                  長崎県\n                  熊本県\n                  大分県\n                  宮崎県\n                  鹿児島県\n                  沖縄県\n                \n              \n            \n              \n                       \n              花火特集2025\n              \n                花火大会をエリアから探す\n                \n                  北海道\n                  東北\n                  関東\n                  甲信越\n                  北陸\n                  東海\n                  関西\n                  中国\n                  四国\n                  九州・沖縄\n                \n\n                花火大会人気ランキング\n                \n                  全国\n                  北海道\n                  東北\n                  関東\n                  甲信越\n                  北陸\n                  東海\n                  関西\n                  中国\n                  四国\n                  九州・沖縄\n                \n                \n                \n                  打ち上げ数ランキング\n                  人出ランキング \n                  行ってみたいランキング\n                  行ってよかったランキング \n                \n                \n                \n                \n                \n                  花火大会カレンダー\n                  5月開催の花火大会\n                   6月開催の花火大会\n                    7月開催の花火大会\n                  8月開催の花火大会           \n                  9月開催の花火大会\n                  10月開催の花火大会\n                            \n                \n                \n               \n                  今日開催の花火大会\n                  明日開催の花火大会                  \n                 \n                \n                \n                  有料席のチケット情報\n                \n                \n                \n                  花火トピックス\n                \n                \n\n              \n            \n            \n            \n          \n          \n            \n\n\n\n\n\n\n\n\n            \n  おすすめ情報\n  \n\n\n\n\n\n\n\n\n\n\n\n\n\n\n\n\n\n\n\n\n\n\n  \n\n\n            \n            \n              人気花火大会ランキング【甲信越】\n                \n                  2025年6月14日 更新\n                  \n                    \n                        1\n                        第41回 咲花温泉水中花火大会\n                      \n                    \n                        2\n                        まき夏まつり 花火大会\n                      \n                    \n                        3\n                        河口湖湖上祭\n                      \n                    \n                        4\n                        長岡まつり大花火大会\n                      \n                    \n                        5\n                        長岡花火ローズファンタジー\n                      \n                  \n                  もっと見る \n                \n            \n            \n            \n              \n  閲覧履歴\n  \n    \n      \n        最近見た花火大会のページはありません。\n      \n    \n    閲覧履歴をもっと見る \n  \n\n            \n            \n  おすすめ記事\n  \n    \n      \n        \n          \n            \n            甲信越で今週末開催されるおすすめ花火大会\n          \n        \n      \n      \n    \n  \n\n                      \n            花火をもっと楽しむ\n            \n              \n\n                \n                  \n                  \n                    開催予定の花火大会\n                    2025年に開催予定の花火大会をご紹介\n                  \n                  \n                \n                  \n                  \n                    花火大会人気ランキング\n                    毎日更新！アクセス数の多い人気花火大会をエリア別にランキング\n                  \n                    \n                   \n                  \n                  \n                    有料席のチケット情報\n                    間近で上がる迫力満点の花火を座ってゆったり楽しもう！！\n                  \n                                         \n                  \n                  \n                  \n                    宿泊付き花火鑑賞ツアー販売中\n                    有料席とホテルをセットにしたウォーカー限定ツアーを販売中！！\n                  \n                   \n                                                   \n                  \n                   \n                  \n                  \n                    屋台のある花火大会をご紹介\n                    花火大会を盛り上げる屋台グルメを楽しめる人気の花火大会10選！\n                  \n                   \n                     \n                 \n                \n                  \n                  \n                    花火カレンダー\n                    花火大会の開催スケジュールをカレンダーでチェック！\n                  \n                  \n      \n                 \n                \n                \n\n                \n                  \n                  \n                    おでかけトピックス\n                    全国の花火大会の開催・中止情報をお届け！新しい花火の楽しみ方もご紹介。\n                  \n                  \n                \n              \n                \n\n                \n                \n\n              \n            \n           \n                      \n          \n            \n\n\n\n\n\n\n\n\n          \n          \n        \n      \n    \n            \n          \n          \n            \n              \n              花火大会2025\n            \n            \n          \n          \n          \n            \n              \n              全国の花火大会の人出ランキング\n            \n            \n          \n          \n          \n            \n              \n              甲信越の花火大会の人出ランキング\n            \n            \n          \n          \n        \n    \n  \n  \n    \n  \n    ウォーカープラス・季節特集\n    \n      ウォーカープラス\n      いちご狩り\n      お花見\n      ゴールデンウィーク\n      花火大会\n      夏休み（夏祭り）\n      紅葉\n      イルミネーション\n    \n    関連サイト\n    \n      レタスクラブ\n      ダ・ヴィンチWeb\n      WEBザテレビジョン\n      MOVIE WALKER PRESS\n      毎日が発見ネット\n      PressWalker\n      \n    \n  \n  \n    \n      \n        利用規約\n        プライバシーポリシー\n        推奨環境\n        お問い合わせ\n        プレスリリース・情報提供\n        媒体資料\n        広告掲載について\n        会社概要\n        利用者情報の外部送信について\n      \n    \n    \n      \n      © KADOKAWA CORPORATION\n    \n  \n\n  \n  \n\n\n\n\n\n\n\n\n\n  \n  \n  \n  \n  \n  \n  \n  \n  \n    {\n      lang: 'ja'\n    }\n  \n\n\n(function(a,e,b,f,g,c,d){a[b]=a[b]||function(){(a[b].q=a[b].q||[]).push(arguments)};c=e.createElement(f);c.async=1;c.src=\"https://www.clarity.ms/tag/\"+g;d=e.getElementsByTagName(f)[0];d.parentNode.insertBefore(c,d)})(window,document,\"clarity\",\"script\",\"f13adjk1bm\");"
      },
      {
        "title": ".plus {fill:url(#gradient);}.font {fill: #fff; }",
        "date": "2025年6月14日",
        "location": "新潟県・長岡市/信濃川河川敷",
        "visitors": "40万人",
        "fireworks": "2万発",
        "rawText": ".plus {fill:url(#gradient);}.font {fill: #fff; }\n            \n            \n          \n\n\n\n\n\n\n\n\n\n\n\n\n\n\n\n\n\n\n\n\n\n\n\n\n\n\n\n\n\n\n\n\n\n      \n    \n    \n      \n      \n    \n    \n  \n\n\n        \n\n\n\n全国約900大会の花火大会情報をお届け！\n\n \n\n\n \n    \n    \n    \n    \n\n                  \n            \n              \n                \n                  花火特集2025\n                  北海道\n                  東北\n                  関東\n                    \n                      東京\n                      神奈川\n                      千葉\n                    \n                  \n                  甲信越\n                  北陸\n                  東海\n                  \n                      愛知\n                    \n                   \n                  関西\n                    \n                      大阪\n                    \n                  \n                  中国\n                  四国\n                  九州・沖縄\n                \n              \n                         \n                \n                エリアから探す\n                \n                人気ランキング\n           \t\t\n                開催予定の花火大会\n                花火カレンダー\n                \n                おうちで金麦\n                \n              \n              \n\n    \t\t\t\n\n\n\n  \n  \n    \n      \n\n\n\n\t\n    \n    \n      \n\n\n\n    \n    \n  \n\n\n\n            \n          \n        \n\n\n\n\n\n\n\n\n\n        \n   2025年の情報に順次更新しておりますが、過去の情報もございます。当日の開催情報は大会主催者に確認ください \n\n\n\n                \n          \n          \n            \n              \n              花火大会2025\n            \n            \n          \n          \n          \n            \n              \n              全国の花火大会の人出ランキング\n            \n            \n          \n          \n          \n            \n              \n              甲信越の花火大会の人出ランキング\n            \n            \n          \n          \n        \n     \n      \n    \n    \n      \n        \n          \n              \n\n            \n            \n              \n                甲信越の花火大会の人出ランキング\n                例年の来場者数をもとにランキング！混雑を予測しておでかけの参考にしよう！\n              \n              \n              \n    \n        注目の花火大会\n        \n          河口湖湖上祭長岡まつり大花火大会\n        \n    \n\n              2025年6月14日 更新\n              エリアを絞り込む\n              \n                \n                \n                甲信越\n                \n                山梨県\n                \n                \n                長野県\n                \n                \n                新潟県\n                \n              \n              その他のランキングから探す\n              \n                \n                  \n                    人気花火大会ランキング\n                    \n                        打ち上げ数ランキング\n                      \n                  \n                  \n                    \n                        行ってみたいランキング\n                      \n                    \n                        行ってよかったランキング\n                      \n                  \n                \n              \n\n              \n              \n                \n                \n                  \n                    \n                      \n                        \n                        第119回 長野えびす講煙火大会\n                      \n                      \n                        \n                        \n                      \n                      \n                        \n                          信州の澄んだ夜空を彩る晩秋の花火\n                          長野県・長野市/長野大橋西側  犀川第2緑地\n                          期間：2025年11月23日(日)\n                            \n                              例年の人出：約40万人\n                              行ってみたい：23\n                              行ってよかった：11\n                              \n                              有料席：あり\n                              屋台：あり\n                            \n                          \n                        \n                      \n                    \n                  \n                \n                \n                \n                \n                  \n                    \n                      \n                        \n                        長岡まつり大花火大会\n                      \n                      \n                        \n                        \n                      \n                      \n                        \n                          復興祈願花火フェニックスは、ほかにはない大迫力\n                          新潟県・長岡市/信濃川河川敷\n                          期間：2025年8月2日(土)・3日(日)\n                            \n                              例年の人出：約34万5000人\n                              行ってみたい：81\n                              行ってよかった：42\n                              \n                              有料席：あり\n                              屋台：あり\n                            \n                          \n                        \n                      \n                    \n                  \n                \n                \n                \n                \n                  \n                    \n                      \n                        \n                        新潟まつり花火大会\n                      \n                      \n                        \n                        \n                      \n                      \n                        \n                          日本一の大河「信濃川」を舞台に繰り広げられる壮大な花火大会\n                          新潟県・新潟市中央区/新潟市中央区信濃川河畔(昭和大橋周辺)\n                          期間：2025年8月10日(日)\n                            \n                              例年の人出：約32万人\n                              行ってみたい：20\n                              行ってよかった：7\n                              \n                              \n                              \n                            \n                          \n                        \n                      \n                    \n                  \n                \n                \n\n\n\n\n\n                \n                \n                  \n                    \n                      \n                        \n                        全国新作花火チャレンジカップ2025\n                      \n                      \n                        \n                        \n                      \n                      \n                        \n                          6年ぶりにリニューアルし、分散方式による競技花火を開催決定\n                          長野県・諏訪市/長野県諏訪市湖畔公園前諏訪湖上\n                          期間：予選：2025年9月6日(土)・13日(土)・20日(土)・27日(土)。決勝：10月26日(日)\n                            \n                              例年の人出：約25万人\n                              行ってみたい：7\n                              行ってよかった：2\n                              \n                              \n                              \n                            \n                          \n                        \n                      \n                    \n                  \n                \n                \n                \n                \n                  \n                    \n                      \n                        \n                        市川三郷町ふるさと夏まつり　第37回「神明の花火大会」\n                      \n                      \n                        \n                        \n                      \n                      \n                        \n                          音楽と彩る約2万発の夜空の芸術\n                          山梨県・西八代郡市川三郷町/三郡橋下流笛吹川河畔\n                          期間：2025年8月7日(木)\n                            \n                              例年の人出：約20万人\n                              行ってみたい：28\n                              行ってよかった：20\n                              \n                              有料席：あり\n                              屋台：あり\n                            \n                          \n                        \n                      \n                    \n                  \n                \n                \n                \n                \n                  \n                    \n                      \n                        \n                        第51回 阿賀野川ござれや花火\n                      \n                      \n                        \n                        \n                      \n                      \n                        \n                          超特大スターマインの花鳥風月をお見逃しなく\n                          新潟県・新潟市北区/阿賀野川松浜橋上流側\n                          期間：2025年8月25日(月)\n                            \n                              例年の人出：20万人\n                              行ってみたい：7\n                              行ってよかった：5\n                              \n                              有料席：あり\n                              \n                            \n                          \n                        \n                      \n                    \n                  \n                \n                \n\n\n\n\n\n\n                \n                \n                  \n                    \n                      \n                        \n                        おぢやまつり大花火大会2024\n                      \n                      \n                        \n                        \n                      \n                      \n                        \n                          超ワイド大スターマインが夜空に咲く\n                          新潟県・小千谷市/信濃川河川敷(旭橋下流)\n                          期間：2024年8月24日(土)おぢやまつりは8月23日(金)～25日(日)の3日間\n                            \n                              例年の人出：18万人\n                              行ってみたい：5\n                              行ってよかった：2\n                              \n                              有料席：あり\n                              \n                            \n                          \n                        \n                      \n                    \n                  \n                \n                \n                \n                \n                  \n                    \n                      \n                        \n                        ぎおん柏崎まつり 海の大花火大会\n                      \n                      \n                        \n                        \n                      \n                      \n                        \n                          尺玉100発一斉打上など豪華な花火がめじろ押し\n                          新潟県・柏崎市/柏崎市中央海岸・みなとまち海浜公園一帯\n                          期間：2025年7月26日(土)\n                            \n                              例年の人出：約17万人\n                              行ってみたい：24\n                              行ってよかった：18\n                              \n                              有料席：あり\n                              屋台：あり\n                            \n                          \n                        \n                      \n                    \n                  \n                \n                \n                \n                \n                  \n                    \n                      \n                        \n                        浅原神社 秋季例大祭奉納大煙火\n                      \n                      \n                        \n                        \n                      \n                      \n                        \n                          四尺玉をはじめ尺玉多数、大迫力の尺玉連発を堪能\n                          新潟県・小千谷市/片貝町浅原神社裏手\n                          期間：2025年9月12日(金)・13日(土)\n                            \n                              例年の人出：約17万人\n                              行ってみたい：15\n                              行ってよかった：11\n                              \n                              有料席：あり\n                              屋台：あり\n                            \n                          \n                        \n                      \n                    \n                  \n                \n                \n                \n                \n                  \n                    \n                      \n                        \n                        河口湖湖上祭\n                      \n                      \n                        \n                        \n                      \n                      \n                        \n                          河口湖の夜空を彩る大迫力の花火\n                          山梨県・南都留郡富士河口湖町/河口湖畔船津浜\n                          期間：2025年8月5日(火)\n                            \n                              例年の人出：12万人\n                              行ってみたい：24\n                              行ってよかった：8\n                              \n                              \n                              屋台：あり\n                            \n                          \n                        \n                      \n                    \n                  \n                \n                \n\n\n\n\n\n                \n                \n              \n              \n              \n  \n    規模の大きな主要花火大会\n  \n\n                            \n              \n              \n              \n                \n                  \n                  1\n                  \n                    \n                      \n                        \n                      \n                      2\n                      \n                    \n                      \n                      3\n                      \n                    \n                      \n                      4\n                      \n                    \n                      \n                      5\n                      \n                        \n                          …\n                        \n                      \n                    \n                  \n                  7\n                  \n                  \n                  次へ\n                  \n                \n              \n              \n              \n\n\n\n\n\n  \n\n\n\n\n\n\n\n\n\n  \n\n\n\n \n            \n\n            \n              \n              \n              \n                カレンダーから花火大会を探す【甲信越】\n                \n  \n  \n    \n      \n        \n          \n          今週末開催の花火大会\n        \n      \n    \n    \n      \n        \n          \n          来週末開催の花火大会\n        \n      \n    \n  \n  \n\n                \n                日付を選んで、その日に開催される花火大会をチェックしよう！\n                              \n              \n                \n                  \n                    \n                    \n                    \n                    7月\n                    \n                    8月\n                    \n                    9月\n                    \n                  \n                  \n                    \n                    \n                      7月開催の花火大会一覧はこちら\n                      \n                        \n                          \n                            月\n                            火\n                            水\n                            木\n                            金\n                            土\n                            日\n                          \n                          \n                          \n                            \n                            \n                            \n                            \n                            \n                            \n                            1\n                                \n                                  \n                                  \n                                  \n                                \n                              \n                            \n                            \n                            \n                            2\n                                \n                                  \n                                  \n                                  \n                                \n                              \n                            \n                            \n                            \n                            3\n                                \n                                  \n                                  \n                                  \n                                \n                              \n                            \n                            \n                            \n                            4\n                                \n                                  \n                                  \n                                  \n                                \n                              \n                            \n                            \n                            \n                            5\n                                \n                                  \n                                  \n                                  \n                                \n                              \n                            \n                            \n                            \n                            6\n                                \n                                  \n                                  \n                                  \n                                \n                              \n                            \n                            \n                          \n                          \n                          \n                            \n                            \n                            7\n                                \n                                  \n                                  \n                                  \n                                \n                              \n                            \n                            \n                            \n                            8\n                                \n                                  \n                                  \n                                  \n                                \n                              \n                            \n                            \n                            \n                            9\n                                \n                                  \n                                  \n                                  \n                                \n                              \n                            \n                            \n                            \n                            10\n                                \n                                  \n                                  \n                                  \n                                \n                              \n                            \n                            \n                            \n                            11\n                                \n                                  \n                                  \n                                  \n                                \n                              \n                            \n                            \n                            \n                            12\n                                \n                                  \n                                  \n                                  \n                                \n                              \n                            \n                            \n                            \n                            13\n                                \n                                  \n                                  \n                                  \n                                \n                              \n                            \n                            \n                          \n                          \n                          \n                            \n                            \n                            14\n                                \n                                  \n                                  \n                                  \n                                \n                              \n                            \n                            \n                            \n                            15\n                                \n                                  \n                                  \n                                  \n                                \n                              \n                            \n                            \n                            \n                            16\n                                \n                                  \n                                  \n                                  \n                                \n                              \n                            \n                            \n                            \n                            17\n                                \n                                  \n                                  \n                                  \n                                \n                              \n                            \n                            \n                            \n                            18\n                                \n                                  \n                                  \n                                  \n                                \n                              \n                            \n                            \n                            \n                            19\n                                \n                                  \n                                  \n                                  \n                                \n                              \n                            \n                            \n                            \n                            20\n                                \n                                  \n                                  \n                                  \n                                \n                              \n                            \n                            \n                          \n                          \n                          \n                            \n                            \n                            21\n                                \n                                  \n                                  \n                                  \n                                \n                              \n                            \n                            \n                            \n                            22\n                                \n                                  \n                                  \n                                  \n                                \n                              \n                            \n                            \n                            \n                            23\n                                \n                                  \n                                  \n                                  \n                                \n                              \n                            \n                            \n                            \n                            24\n                                \n                                  \n                                  \n                                  \n                                \n                              \n                            \n                            \n                            \n                            25\n                                \n                                  \n                                  \n                                  \n                                \n                              \n                            \n                            \n                            \n                            26\n                                \n                                  \n                                  \n                                  \n                                \n                              \n                            \n                            \n                            \n                            27\n                                \n                                  \n                                  \n                                  \n                                \n                              \n                            \n                            \n                          \n                          \n                          \n                            \n                            \n                            28\n                                \n                                  \n                                  \n                                  \n                                \n                              \n                            \n                            \n                            \n                            29\n                                \n                                  \n                                  \n                                  \n                                \n                              \n                            \n                            \n                            \n                            30\n                                \n                                  \n                                  \n                                  \n                                \n                              \n                            \n                            \n                            \n                            31\n                                \n                                  \n                                  \n                                  \n                                \n                              \n                            \n                            \n                            \n                            \n                            \n                            \n                            \n                            \n                            \n                            \n                            \n                            \n                            \n                            \n                          \n                          \n                        \n                      \n                    \n                    \n                    \n                    \n                      8月開催の花火大会一覧はこちら\n                      \n                        \n                          \n                            月\n                            火\n                            水\n                            木\n                            金\n                            土\n                            日\n                          \n                          \n                          \n                            \n                            \n                            \n                            \n                            \n                            \n                            \n                            \n                            \n                            \n                            \n                            \n                            \n                            \n                            \n                            \n                            \n                            \n                            1\n                                \n                                  \n                                  \n                                  \n                                \n                              \n                            \n                            \n                            \n                            2\n                                \n                                  \n                                  \n                                  \n                                \n                              \n                            \n                            \n                            \n                            3\n                                \n                                  \n                                  \n                                  \n                                \n                              \n                            \n                            \n                          \n                          \n                          \n                            \n                            \n                            4\n                                \n                                  \n                                  \n                                  \n                                \n                              \n                            \n                            \n                            \n                            5\n                                \n                                  \n                                  \n                                  \n                                \n                              \n                            \n                            \n                            \n                            6\n                                \n                                  \n                                  \n                                  \n                                \n                              \n                            \n                            \n                            \n                            7\n                                \n                                  \n                                  \n                                  \n                                \n                              \n                            \n                            \n                            \n                            8\n                                \n                                  \n                                  \n                                  \n                                \n                              \n                            \n                            \n                            \n                            9\n                                \n                                  \n                                  \n                                  \n                                \n                              \n                            \n                            \n                            \n                            10\n                                \n                                  \n                                  \n                                  \n                                \n                              \n                            \n                            \n                          \n                          \n                          \n                            \n                            \n                            11\n                                \n                                  \n                                  \n                                  \n                                \n                              \n                            \n                            \n                            \n                            12\n                                \n                                  \n                                  \n                                  \n                                \n                              \n                            \n                            \n                            \n                            13\n                                \n                                  \n                                  \n                                  \n                                \n                              \n                            \n                            \n                            \n                            14\n                                \n                                  \n                                  \n                                  \n                                \n                              \n                            \n                            \n                            \n                            15\n                                \n                                  \n                                  \n                                  \n                                \n                              \n                            \n                            \n                            \n                            16\n                                \n                                  \n                                  \n                                  \n                                \n                              \n                            \n                            \n                            \n                            17\n                                \n                                  \n                                  \n                                  \n                                \n                              \n                            \n                            \n                          \n                          \n                          \n                            \n                            \n                            18\n                                \n                                  \n                                  \n                                  \n                                \n                              \n                            \n                            \n                            \n                            19\n                                \n                                  \n                                  \n                                  \n                                \n                              \n                            \n                            \n                            \n                            20\n                                \n                                  \n                                  \n                                  \n                                \n                              \n                            \n                            \n                            \n                            21\n                                \n                                  \n                                  \n                                  \n                                \n                              \n                            \n                            \n                            \n                            22\n                                \n                                  \n                                  \n                                  \n                                \n                              \n                            \n                            \n                            \n                            23\n                                \n                                  \n                                  \n                                  \n                                \n                              \n                            \n                            \n                            \n                            24\n                                \n                                  \n                                  \n                                  \n                                \n                              \n                            \n                            \n                          \n                          \n                          \n                            \n                            \n                            25\n                                \n                                  \n                                  \n                                  \n                                \n                              \n                            \n                            \n                            \n                            26\n                                \n                                  \n                                  \n                                  \n                                \n                              \n                            \n                            \n                            \n                            27\n                                \n                                  \n                                  \n                                  \n                                \n                              \n                            \n                            \n                            \n                            28\n                                \n                                  \n                                  \n                                  \n                                \n                              \n                            \n                            \n                            \n                            29\n                                \n                                  \n                                  \n                                  \n                                \n                              \n                            \n                            \n                            \n                            30\n                                \n                                  \n                                  \n                                  \n                                \n                              \n                            \n                            \n                            \n                            31\n                                \n                                  \n                                  \n                                  \n                                \n                              \n                            \n                            \n                          \n                          \n                          \n                            \n                            \n                            \n                            \n                            \n                            \n                            \n                            \n                            \n                            \n                            \n                            \n                            \n                            \n                            \n                            \n                            \n                            \n                            \n                            \n                            \n                            \n                            \n                            \n                            \n                            \n                            \n                            \n                            \n                          \n                          \n                        \n                      \n                    \n                    \n                    \n                    \n                      9月開催の花火大会一覧はこちら\n                      \n                        \n                          \n                            月\n                            火\n                            水\n                            木\n                            金\n                            土\n                            日\n                          \n                          \n                          \n                            \n                            \n                            1\n                                \n                                  \n                                  \n                                  \n                                \n                              \n                            \n                            \n                            \n                            2\n                                \n                                  \n                                  \n                                  \n                                \n                              \n                            \n                            \n                            \n                            3\n                                \n                                  \n                                  \n                                  \n                                \n                              \n                            \n                            \n                            \n                            4\n                                \n                                  \n                                  \n                                  \n                                \n                              \n                            \n                            \n                            \n                            5\n                                \n                                  \n                                  \n                                  \n                                \n                              \n                            \n                            \n                            \n                            6\n                                \n                                  \n                                  \n                                  \n                                \n                              \n                            \n                            \n                            \n                            7\n                                \n                                  \n                                  \n                                  \n                                \n                              \n                            \n                            \n                          \n                          \n                          \n                            \n                            \n                            8\n                                \n                                  \n                                  \n                                  \n                                \n                              \n                            \n                            \n                            \n                            9\n                                \n                                  \n                                  \n                                  \n                                \n                              \n                            \n                            \n                            \n                            10\n                                \n                                  \n                                  \n                                  \n                                \n                              \n                            \n                            \n                            \n                            11\n                                \n                                  \n                                  \n                                  \n                                \n                              \n                            \n                            \n                            \n                            12\n                                \n                                  \n                                  \n                                  \n                                \n                              \n                            \n                            \n                            \n                            13\n                                \n                                  \n                                  \n                                  \n                                \n                              \n                            \n                            \n                            \n                            14\n                                \n                                  \n                                  \n                                  \n                                \n                              \n                            \n                            \n                          \n                          \n                          \n                            \n                            \n                            15\n                                \n                                  \n                                  \n                                  \n                                \n                              \n                            \n                            \n                            \n                            16\n                                \n                                  \n                                  \n                                  \n                                \n                              \n                            \n                            \n                            \n                            17\n                                \n                                  \n                                  \n                                  \n                                \n                              \n                            \n                            \n                            \n                            18\n                                \n                                  \n                                  \n                                  \n                                \n                              \n                            \n                            \n                            \n                            19\n                                \n                                  \n                                  \n                                  \n                                \n                              \n                            \n                            \n                            \n                            20\n                                \n                                  \n                                  \n                                  \n                                \n                              \n                            \n                            \n                            \n                            21\n                                \n                                  \n                                  \n                                  \n                                \n                              \n                            \n                            \n                          \n                          \n                          \n                            \n                            \n                            22\n                                \n                                  \n                                  \n                                  \n                                \n                              \n                            \n                            \n                            \n                            23\n                                \n                                  \n                                  \n                                  \n                                \n                              \n                            \n                            \n                            \n                            24\n                                \n                                  \n                                  \n                                  \n                                \n                              \n                            \n                            \n                            \n                            25\n                                \n                                  \n                                  \n                                  \n                                \n                              \n                            \n                            \n                            \n                            26\n                                \n                                  \n                                  \n                                  \n                                \n                              \n                            \n                            \n                            \n                            27\n                                \n                                  \n                                  \n                                  \n                                \n                              \n                            \n                            \n                            \n                            28\n                                \n                                  \n                                  \n                                  \n                                \n                              \n                            \n                            \n                          \n                          \n                          \n                            \n                            \n                            29\n                                \n                                  \n                                  \n                                  \n                                \n                              \n                            \n                            \n                            \n                            30\n                                \n                                  \n                                  \n                                  \n                                \n                              \n                            \n                            \n                            \n                            \n                            \n                            \n                            \n                            \n                            \n                            \n                            \n                            \n                            \n                            \n                            \n                            \n                            \n                            \n                            \n                            \n                            \n                            \n                          \n                          \n                        \n                      \n                    \n                    \n                    \n\n                    \n  \n    規模の大きな主要花火大会\n  \n\n                  \n                  \n                  \n                \n              \n              \n              \n                          \n              \n                花火トピックス\n                全国の花火大会の開催・中止情報をお届け！注目の花火大会や、知って得する花火ネタをご紹介。\n              \n              \n                \n                  \n                  \n                      \n                      2025年も「金麦」“夏の味”の発売スタート！ほかの季節の金麦となにが違う？四季の味へのこだわりを聞いてみた\n                      \n                        PR\n                      \n                      全国\n                      \n                        2025年6月12日 10:00 更新\n                        \n                      \n                    \n                  \n                  \n                      \n                      「金麦」“夏の味”を編集部員が体験！ 「おうちで金麦花火セット」が当たるスペシャルなキャンペーンも紹介\n                      \n                        PR\n                      \n                      全国\n                      \n                        2025年6月12日 10:00 更新\n                        \n                      \n                    \n                  \n                  \n                      \n                      「日本三大花火大会」とは？日本最大規模の超大型花火大会をチェック！\n                      \n                        \n                      \n                      全国\n                      \n                        2025年6月11日 14:30 更新\n                        \n                      \n                    \n                  \n                \n              \n              \n                花火トピックスをもっと見る\n              \n            \n              \n                          \n              甲信越の花火大会を探す\n              \n                \n                  周辺のエリア・都道府県から探す\n                \n                \n                  \n                  山梨県\n                  \n                  長野県\n                  \n                  新潟県\n                  \n                \n\n                \n                \n                  開催状況から花火大会を探す\n                  \n                    開催予定の花火大会\n                    \n                  \n                \n                \n\n                花火カレンダーから探す\n                  \n\n                  \n                    \n                      \n                        \n                          甲信越の花火カレンダー\n                        \n                      \n                      \n                        \n                          今日開催の花火大会\n                        \n                      \n                      \n                        \n                          明日開催の花火大会\n                        \n                      \n                    \n                  \n\n                  開催される月から探す\n                    \n\n                    \n                        6月\n                      \n                        7月\n                      \n                        8月\n                      \n                        9月\n                      \n                        10月\n                      \n                        11月\n                      \n\n                ランキングから探す\n                \n                  \n                    \n                      \n                        甲信越の人気花火大会ランキング\n                      \n                      \n                        甲信越の行ってみたい花火大会ランキング\n                      \n                    \n                    \n                      \n                        甲信越の行ってよかった花火大会ランキング\n                      \n                      \n                        甲信越の打ち上げ数ランキング\n                      \n                    \n                    \n                      \n                        甲信越の人出ランキング\n                      \n                    \n                  \n                \n              \n            \n              \n                          \n              都道府県から花火大会を探す\n              \n                \n                  北海道\n                  北海道\n                \n                \n                  東　北\n                  宮城県\n                  青森県\n                  岩手県\n                  秋田県\n                  山形県\n                  福島県\n                \n                \n                  関　東\n                  東京都\n                  神奈川県\n                  千葉県\n                  埼玉県\n                  群馬県\n                  栃木県\n                  茨城県\n                \n                \n                  甲信越\n                  山梨県\n                  長野県\n                  新潟県\n                \n                \n                  北　陸\n                  石川県\n                  富山県\n                  福井県\n                \n                \n                  東　海\n                  愛知県\n                  岐阜県\n                  三重県\n                  静岡県\n                \n                \n                  関　西\n                  大阪府\n                  京都府\n                  兵庫県\n                  奈良県\n                  和歌山県\n                  滋賀県\n                \n                \n                  中　国\n                  広島県\n                  岡山県\n                  山口県\n                  鳥取県\n                  島根県\n                \n                \n                  四　国\n                  香川県\n                  愛媛県\n                  徳島県\n                  高知県\n                \n                \n                  九州・沖縄\n                  福岡県\n                  佐賀県\n                  長崎県\n                  熊本県\n                  大分県\n                  宮崎県\n                  鹿児島県\n                  沖縄県\n                \n              \n            \n              \n                       \n              花火特集2025\n              \n                花火大会をエリアから探す\n                \n                  北海道\n                  東北\n                  関東\n                  甲信越\n                  北陸\n                  東海\n                  関西\n                  中国\n                  四国\n                  九州・沖縄\n                \n\n                花火大会人気ランキング\n                \n                  全国\n                  北海道\n                  東北\n                  関東\n                  甲信越\n                  北陸\n                  東海\n                  関西\n                  中国\n                  四国\n                  九州・沖縄\n                \n                \n                \n                  打ち上げ数ランキング\n                  人出ランキング \n                  行ってみたいランキング\n                  行ってよかったランキング \n                \n                \n                \n                \n                \n                  花火大会カレンダー\n                  5月開催の花火大会\n                   6月開催の花火大会\n                    7月開催の花火大会\n                  8月開催の花火大会           \n                  9月開催の花火大会\n                  10月開催の花火大会\n                            \n                \n                \n               \n                  今日開催の花火大会\n                  明日開催の花火大会                  \n                 \n                \n                \n                  有料席のチケット情報\n                \n                \n                \n                  花火トピックス\n                \n                \n\n              \n            \n            \n            \n          \n          \n            \n\n\n\n\n\n\n\n\n            \n  おすすめ情報\n  \n\n\n\n\n\n\n\n\n\n\n\n\n\n\n\n\n\n\n\n\n\n\n  \n\n\n            \n            \n              人気花火大会ランキング【甲信越】\n                \n                  2025年6月14日 更新\n                  \n                    \n                        1\n                        第41回 咲花温泉水中花火大会\n                      \n                    \n                        2\n                        まき夏まつり 花火大会\n                      \n                    \n                        3\n                        河口湖湖上祭\n                      \n                    \n                        4\n                        長岡まつり大花火大会\n                      \n                    \n                        5\n                        長岡花火ローズファンタジー\n                      \n                  \n                  もっと見る \n                \n            \n            \n            \n              \n  閲覧履歴\n  \n    \n      \n        最近見た花火大会のページはありません。\n      \n    \n    閲覧履歴をもっと見る \n  \n\n            \n            \n  おすすめ記事\n  \n    \n      \n        \n          \n            \n            甲信越で今週末開催されるおすすめ花火大会\n          \n        \n      \n      \n    \n  \n\n                      \n            花火をもっと楽しむ\n            \n              \n\n                \n                  \n                  \n                    開催予定の花火大会\n                    2025年に開催予定の花火大会をご紹介\n                  \n                  \n                \n                  \n                  \n                    花火大会人気ランキング\n                    毎日更新！アクセス数の多い人気花火大会をエリア別にランキング\n                  \n                    \n                   \n                  \n                  \n                    有料席のチケット情報\n                    間近で上がる迫力満点の花火を座ってゆったり楽しもう！！\n                  \n                                         \n                  \n                  \n                  \n                    宿泊付き花火鑑賞ツアー販売中\n                    有料席とホテルをセットにしたウォーカー限定ツアーを販売中！！\n                  \n                   \n                                                   \n                  \n                   \n                  \n                  \n                    屋台のある花火大会をご紹介\n                    花火大会を盛り上げる屋台グルメを楽しめる人気の花火大会10選！\n                  \n                   \n                     \n                 \n                \n                  \n                  \n                    花火カレンダー\n                    花火大会の開催スケジュールをカレンダーでチェック！\n                  \n                  \n      \n                 \n                \n                \n\n                \n                  \n                  \n                    おでかけトピックス\n                    全国の花火大会の開催・中止情報をお届け！新しい花火の楽しみ方もご紹介。\n                  \n                  \n                \n              \n                \n\n                \n                \n\n              \n            \n           \n                      \n          \n            \n\n\n\n\n\n\n\n\n          \n          \n        \n      \n    \n            \n          \n          \n            \n              \n              花火大会2025\n            \n            \n          \n          \n          \n            \n              \n              全国の花火大会の人出ランキング\n            \n            \n          \n          \n          \n            \n              \n              甲信越の花火大会の人出ランキング"
      },
      {
        "title": "甲信越の花火大会の人出ランキング",
        "date": "2025年6月14日",
        "location": "新潟県・長岡市/信濃川河川敷",
        "visitors": "40万人",
        "fireworks": "2万発",
        "rawText": "甲信越の花火大会の人出ランキング\n                例年の来場者数をもとにランキング！混雑を予測しておでかけの参考にしよう！\n              \n              \n              \n    \n        注目の花火大会\n        \n          河口湖湖上祭長岡まつり大花火大会\n        \n    \n\n              2025年6月14日 更新\n              エリアを絞り込む\n              \n                \n                \n                甲信越\n                \n                山梨県\n                \n                \n                長野県\n                \n                \n                新潟県\n                \n              \n              その他のランキングから探す\n              \n                \n                  \n                    人気花火大会ランキング\n                    \n                        打ち上げ数ランキング\n                      \n                  \n                  \n                    \n                        行ってみたいランキング\n                      \n                    \n                        行ってよかったランキング\n                      \n                  \n                \n              \n\n              \n              \n                \n                \n                  \n                    \n                      \n                        \n                        第119回 長野えびす講煙火大会\n                      \n                      \n                        \n                        \n                      \n                      \n                        \n                          信州の澄んだ夜空を彩る晩秋の花火\n                          長野県・長野市/長野大橋西側  犀川第2緑地\n                          期間：2025年11月23日(日)\n                            \n                              例年の人出：約40万人\n                              行ってみたい：23\n                              行ってよかった：11\n                              \n                              有料席：あり\n                              屋台：あり\n                            \n                          \n                        \n                      \n                    \n                  \n                \n                \n                \n                \n                  \n                    \n                      \n                        \n                        長岡まつり大花火大会\n                      \n                      \n                        \n                        \n                      \n                      \n                        \n                          復興祈願花火フェニックスは、ほかにはない大迫力\n                          新潟県・長岡市/信濃川河川敷\n                          期間：2025年8月2日(土)・3日(日)\n                            \n                              例年の人出：約34万5000人\n                              行ってみたい：81\n                              行ってよかった：42\n                              \n                              有料席：あり\n                              屋台：あり\n                            \n                          \n                        \n                      \n                    \n                  \n                \n                \n                \n                \n                  \n                    \n                      \n                        \n                        新潟まつり花火大会\n                      \n                      \n                        \n                        \n                      \n                      \n                        \n                          日本一の大河「信濃川」を舞台に繰り広げられる壮大な花火大会\n                          新潟県・新潟市中央区/新潟市中央区信濃川河畔(昭和大橋周辺)\n                          期間：2025年8月10日(日)\n                            \n                              例年の人出：約32万人\n                              行ってみたい：20\n                              行ってよかった：7\n                              \n                              \n                              \n                            \n                          \n                        \n                      \n                    \n                  \n                \n                \n\n\n\n\n\n                \n                \n                  \n                    \n                      \n                        \n                        全国新作花火チャレンジカップ2025\n                      \n                      \n                        \n                        \n                      \n                      \n                        \n                          6年ぶりにリニューアルし、分散方式による競技花火を開催決定\n                          長野県・諏訪市/長野県諏訪市湖畔公園前諏訪湖上\n                          期間：予選：2025年9月6日(土)・13日(土)・20日(土)・27日(土)。決勝：10月26日(日)\n                            \n                              例年の人出：約25万人\n                              行ってみたい：7\n                              行ってよかった：2\n                              \n                              \n                              \n                            \n                          \n                        \n                      \n                    \n                  \n                \n                \n                \n                \n                  \n                    \n                      \n                        \n                        市川三郷町ふるさと夏まつり　第37回「神明の花火大会」\n                      \n                      \n                        \n                        \n                      \n                      \n                        \n                          音楽と彩る約2万発の夜空の芸術\n                          山梨県・西八代郡市川三郷町/三郡橋下流笛吹川河畔\n                          期間：2025年8月7日(木)\n                            \n                              例年の人出：約20万人\n                              行ってみたい：28\n                              行ってよかった：20\n                              \n                              有料席：あり\n                              屋台：あり\n                            \n                          \n                        \n                      \n                    \n                  \n                \n                \n                \n                \n                  \n                    \n                      \n                        \n                        第51回 阿賀野川ござれや花火\n                      \n                      \n                        \n                        \n                      \n                      \n                        \n                          超特大スターマインの花鳥風月をお見逃しなく\n                          新潟県・新潟市北区/阿賀野川松浜橋上流側\n                          期間：2025年8月25日(月)\n                            \n                              例年の人出：20万人\n                              行ってみたい：7\n                              行ってよかった：5\n                              \n                              有料席：あり\n                              \n                            \n                          \n                        \n                      \n                    \n                  \n                \n                \n\n\n\n\n\n\n                \n                \n                  \n                    \n                      \n                        \n                        おぢやまつり大花火大会2024\n                      \n                      \n                        \n                        \n                      \n                      \n                        \n                          超ワイド大スターマインが夜空に咲く\n                          新潟県・小千谷市/信濃川河川敷(旭橋下流)\n                          期間：2024年8月24日(土)おぢやまつりは8月23日(金)～25日(日)の3日間\n                            \n                              例年の人出：18万人\n                              行ってみたい：5\n                              行ってよかった：2\n                              \n                              有料席：あり\n                              \n                            \n                          \n                        \n                      \n                    \n                  \n                \n                \n                \n                \n                  \n                    \n                      \n                        \n                        ぎおん柏崎まつり 海の大花火大会\n                      \n                      \n                        \n                        \n                      \n                      \n                        \n                          尺玉100発一斉打上など豪華な花火がめじろ押し\n                          新潟県・柏崎市/柏崎市中央海岸・みなとまち海浜公園一帯\n                          期間：2025年7月26日(土)\n                            \n                              例年の人出：約17万人\n                              行ってみたい：24\n                              行ってよかった：18\n                              \n                              有料席：あり\n                              屋台：あり\n                            \n                          \n                        \n                      \n                    \n                  \n                \n                \n                \n                \n                  \n                    \n                      \n                        \n                        浅原神社 秋季例大祭奉納大煙火\n                      \n                      \n                        \n                        \n                      \n                      \n                        \n                          四尺玉をはじめ尺玉多数、大迫力の尺玉連発を堪能\n                          新潟県・小千谷市/片貝町浅原神社裏手\n                          期間：2025年9月12日(金)・13日(土)\n                            \n                              例年の人出：約17万人\n                              行ってみたい：15\n                              行ってよかった：11\n                              \n                              有料席：あり\n                              屋台：あり\n                            \n                          \n                        \n                      \n                    \n                  \n                \n                \n                \n                \n                  \n                    \n                      \n                        \n                        河口湖湖上祭\n                      \n                      \n                        \n                        \n                      \n                      \n                        \n                          河口湖の夜空を彩る大迫力の花火\n                          山梨県・南都留郡富士河口湖町/河口湖畔船津浜\n                          期間：2025年8月5日(火)\n                            \n                              例年の人出：12万人\n                              行ってみたい：24\n                              行ってよかった：8\n                              \n                              \n                              屋台：あり\n                            \n                          \n                        \n                      \n                    \n                  \n                \n                \n\n\n\n\n\n                \n                \n              \n              \n              \n  \n    規模の大きな主要花火大会\n  \n\n                            \n              \n              \n              \n                \n                  \n                  1\n                  \n                    \n                      \n                        \n                      \n                      2\n                      \n                    \n                      \n                      3\n                      \n                    \n                      \n                      4\n                      \n                    \n                      \n                      5\n                      \n                        \n                          …\n                        \n                      \n                    \n                  \n                  7\n                  \n                  \n                  次へ\n                  \n                \n              \n              \n              \n\n\n\n\n\n  \n\n\n\n\n\n\n\n\n\n  \n\n\n\n \n            \n\n            \n              \n              \n              \n                カレンダーから花火大会を探す【甲信越】\n                \n  \n  \n    \n      \n        \n          \n          今週末開催の花火大会\n        \n      \n    \n    \n      \n        \n          \n          来週末開催の花火大会\n        \n      \n    \n  \n  \n\n                \n                日付を選んで、その日に開催される花火大会をチェックしよう！\n                              \n              \n                \n                  \n                    \n                    \n                    \n                    7月\n                    \n                    8月\n                    \n                    9月\n                    \n                  \n                  \n                    \n                    \n                      7月開催の花火大会一覧はこちら\n                      \n                        \n                          \n                            月\n                            火\n                            水\n                            木\n                            金\n                            土\n                            日\n                          \n                          \n                          \n                            \n                            \n                            \n                            \n                            \n                            \n                            1\n                                \n                                  \n                                  \n                                  \n                                \n                              \n                            \n                            \n                            \n                            2\n                                \n                                  \n                                  \n                                  \n                                \n                              \n                            \n                            \n                            \n                            3\n                                \n                                  \n                                  \n                                  \n                                \n                              \n                            \n                            \n                            \n                            4\n                                \n                                  \n                                  \n                                  \n                                \n                              \n                            \n                            \n                            \n                            5\n                                \n                                  \n                                  \n                                  \n                                \n                              \n                            \n                            \n                            \n                            6\n                                \n                                  \n                                  \n                                  \n                                \n                              \n                            \n                            \n                          \n                          \n                          \n                            \n                            \n                            7\n                                \n                                  \n                                  \n                                  \n                                \n                              \n                            \n                            \n                            \n                            8\n                                \n                                  \n                                  \n                                  \n                                \n                              \n                            \n                            \n                            \n                            9\n                                \n                                  \n                                  \n                                  \n                                \n                              \n                            \n                            \n                            \n                            10\n                                \n                                  \n                                  \n                                  \n                                \n                              \n                            \n                            \n                            \n                            11\n                                \n                                  \n                                  \n                                  \n                                \n                              \n                            \n                            \n                            \n                            12\n                                \n                                  \n                                  \n                                  \n                                \n                              \n                            \n                            \n                            \n                            13\n                                \n                                  \n                                  \n                                  \n                                \n                              \n                            \n                            \n                          \n                          \n                          \n                            \n                            \n                            14\n                                \n                                  \n                                  \n                                  \n                                \n                              \n                            \n                            \n                            \n                            15\n                                \n                                  \n                                  \n                                  \n                                \n                              \n                            \n                            \n                            \n                            16\n                                \n                                  \n                                  \n                                  \n                                \n                              \n                            \n                            \n                            \n                            17\n                                \n                                  \n                                  \n                                  \n                                \n                              \n                            \n                            \n                            \n                            18\n                                \n                                  \n                                  \n                                  \n                                \n                              \n                            \n                            \n                            \n                            19\n                                \n                                  \n                                  \n                                  \n                                \n                              \n                            \n                            \n                            \n                            20\n                                \n                                  \n                                  \n                                  \n                                \n                              \n                            \n                            \n                          \n                          \n                          \n                            \n                            \n                            21\n                                \n                                  \n                                  \n                                  \n                                \n                              \n                            \n                            \n                            \n                            22\n                                \n                                  \n                                  \n                                  \n                                \n                              \n                            \n                            \n                            \n                            23\n                                \n                                  \n                                  \n                                  \n                                \n                              \n                            \n                            \n                            \n                            24\n                                \n                                  \n                                  \n                                  \n                                \n                              \n                            \n                            \n                            \n                            25\n                                \n                                  \n                                  \n                                  \n                                \n                              \n                            \n                            \n                            \n                            26\n                                \n                                  \n                                  \n                                  \n                                \n                              \n                            \n                            \n                            \n                            27\n                                \n                                  \n                                  \n                                  \n                                \n                              \n                            \n                            \n                          \n                          \n                          \n                            \n                            \n                            28\n                                \n                                  \n                                  \n                                  \n                                \n                              \n                            \n                            \n                            \n                            29\n                                \n                                  \n                                  \n                                  \n                                \n                              \n                            \n                            \n                            \n                            30\n                                \n                                  \n                                  \n                                  \n                                \n                              \n                            \n                            \n                            \n                            31\n                                \n                                  \n                                  \n                                  \n                                \n                              \n                            \n                            \n                            \n                            \n                            \n                            \n                            \n                            \n                            \n                            \n                            \n                            \n                            \n                            \n                          \n                          \n                        \n                      \n                    \n                    \n                    \n                    \n                      8月開催の花火大会一覧はこちら\n                      \n                        \n                          \n                            月\n                            火\n                            水\n                            木\n                            金\n                            土\n                            日\n                          \n                          \n                          \n                            \n                            \n                            \n                            \n                            \n                            \n                            \n                            \n                            \n                            \n                            \n                            \n                            \n                            \n                            \n                            \n                            \n                            \n                            1\n                                \n                                  \n                                  \n                                  \n                                \n                              \n                            \n                            \n                            \n                            2\n                                \n                                  \n                                  \n                                  \n                                \n                              \n                            \n                            \n                            \n                            3\n                                \n                                  \n                                  \n                                  \n                                \n                              \n                            \n                            \n                          \n                          \n                          \n                            \n                            \n                            4\n                                \n                                  \n                                  \n                                  \n                                \n                              \n                            \n                            \n                            \n                            5\n                                \n                                  \n                                  \n                                  \n                                \n                              \n                            \n                            \n                            \n                            6\n                                \n                                  \n                                  \n                                  \n                                \n                              \n                            \n                            \n                            \n                            7\n                                \n                                  \n                                  \n                                  \n                                \n                              \n                            \n                            \n                            \n                            8\n                                \n                                  \n                                  \n                                  \n                                \n                              \n                            \n                            \n                            \n                            9\n                                \n                                  \n                                  \n                                  \n                                \n                              \n                            \n                            \n                            \n                            10\n                                \n                                  \n                                  \n                                  \n                                \n                              \n                            \n                            \n                          \n                          \n                          \n                            \n                            \n                            11\n                                \n                                  \n                                  \n                                  \n                                \n                              \n                            \n                            \n                            \n                            12\n                                \n                                  \n                                  \n                                  \n                                \n                              \n                            \n                            \n                            \n                            13\n                                \n                                  \n                                  \n                                  \n                                \n                              \n                            \n                            \n                            \n                            14\n                                \n                                  \n                                  \n                                  \n                                \n                              \n                            \n                            \n                            \n                            15\n                                \n                                  \n                                  \n                                  \n                                \n                              \n                            \n                            \n                            \n                            16\n                                \n                                  \n                                  \n                                  \n                                \n                              \n                            \n                            \n                            \n                            17\n                                \n                                  \n                                  \n                                  \n                                \n                              \n                            \n                            \n                          \n                          \n                          \n                            \n                            \n                            18\n                                \n                                  \n                                  \n                                  \n                                \n                              \n                            \n                            \n                            \n                            19\n                                \n                                  \n                                  \n                                  \n                                \n                              \n                            \n                            \n                            \n                            20\n                                \n                                  \n                                  \n                                  \n                                \n                              \n                            \n                            \n                            \n                            21\n                                \n                                  \n                                  \n                                  \n                                \n                              \n                            \n                            \n                            \n                            22\n                                \n                                  \n                                  \n                                  \n                                \n                              \n                            \n                            \n                            \n                            23\n                                \n                                  \n                                  \n                                  \n                                \n                              \n                            \n                            \n                            \n                            24\n                                \n                                  \n                                  \n                                  \n                                \n                              \n                            \n                            \n                          \n                          \n                          \n                            \n                            \n                            25\n                                \n                                  \n                                  \n                                  \n                                \n                              \n                            \n                            \n                            \n                            26\n                                \n                                  \n                                  \n                                  \n                                \n                              \n                            \n                            \n                            \n                            27\n                                \n                                  \n                                  \n                                  \n                                \n                              \n                            \n                            \n                            \n                            28\n                                \n                                  \n                                  \n                                  \n                                \n                              \n                            \n                            \n                            \n                            29\n                                \n                                  \n                                  \n                                  \n                                \n                              \n                            \n                            \n                            \n                            30\n                                \n                                  \n                                  \n                                  \n                                \n                              \n                            \n                            \n                            \n                            31\n                                \n                                  \n                                  \n                                  \n                                \n                              \n                            \n                            \n                          \n                          \n                          \n                            \n                            \n                            \n                            \n                            \n                            \n                            \n                            \n                            \n                            \n                            \n                            \n                            \n                            \n                            \n                            \n                            \n                            \n                            \n                            \n                            \n                            \n                            \n                            \n                            \n                            \n                            \n                            \n                            \n                          \n                          \n                        \n                      \n                    \n                    \n                    \n                    \n                      9月開催の花火大会一覧はこちら\n                      \n                        \n                          \n                            月\n                            火\n                            水\n                            木\n                            金\n                            土\n                            日\n                          \n                          \n                          \n                            \n                            \n                            1\n                                \n                                  \n                                  \n                                  \n                                \n                              \n                            \n                            \n                            \n                            2\n                                \n                                  \n                                  \n                                  \n                                \n                              \n                            \n                            \n                            \n                            3\n                                \n                                  \n                                  \n                                  \n                                \n                              \n                            \n                            \n                            \n                            4\n                                \n                                  \n                                  \n                                  \n                                \n                              \n                            \n                            \n                            \n                            5\n                                \n                                  \n                                  \n                                  \n                                \n                              \n                            \n                            \n                            \n                            6\n                                \n                                  \n                                  \n                                  \n                                \n                              \n                            \n                            \n                            \n                            7\n                                \n                                  \n                                  \n                                  \n                                \n                              \n                            \n                            \n                          \n                          \n                          \n                            \n                            \n                            8\n                                \n                                  \n                                  \n                                  \n                                \n                              \n                            \n                            \n                            \n                            9\n                                \n                                  \n                                  \n                                  \n                                \n                              \n                            \n                            \n                            \n                            10\n                                \n                                  \n                                  \n                                  \n                                \n                              \n                            \n                            \n                            \n                            11\n                                \n                                  \n                                  \n                                  \n                                \n                              \n                            \n                            \n                            \n                            12\n                                \n                                  \n                                  \n                                  \n                                \n                              \n                            \n                            \n                            \n                            13\n                                \n                                  \n                                  \n                                  \n                                \n                              \n                            \n                            \n                            \n                            14\n                                \n                                  \n                                  \n                                  \n                                \n                              \n                            \n                            \n                          \n                          \n                          \n                            \n                            \n                            15\n                                \n                                  \n                                  \n                                  \n                                \n                              \n                            \n                            \n                            \n                            16\n                                \n                                  \n                                  \n                                  \n                                \n                              \n                            \n                            \n                            \n                            17\n                                \n                                  \n                                  \n                                  \n                                \n                              \n                            \n                            \n                            \n                            18\n                                \n                                  \n                                  \n                                  \n                                \n                              \n                            \n                            \n                            \n                            19\n                                \n                                  \n                                  \n                                  \n                                \n                              \n                            \n                            \n                            \n                            20\n                                \n                                  \n                                  \n                                  \n                                \n                              \n                            \n                            \n                            \n                            21\n                                \n                                  \n                                  \n                                  \n                                \n                              \n                            \n                            \n                          \n                          \n                          \n                            \n                            \n                            22\n                                \n                                  \n                                  \n                                  \n                                \n                              \n                            \n                            \n                            \n                            23\n                                \n                                  \n                                  \n                                  \n                                \n                              \n                            \n                            \n                            \n                            24\n                                \n                                  \n                                  \n                                  \n                                \n                              \n                            \n                            \n                            \n                            25\n                                \n                                  \n                                  \n                                  \n                                \n                              \n                            \n                            \n                            \n                            26\n                                \n                                  \n                                  \n                                  \n                                \n                              \n                            \n                            \n                            \n                            27\n                                \n                                  \n                                  \n                                  \n                                \n                              \n                            \n                            \n                            \n                            28\n                                \n                                  \n                                  \n                                  \n                                \n                              \n                            \n                            \n                          \n                          \n                          \n                            \n                            \n                            29\n                                \n                                  \n                                  \n                                  \n                                \n                              \n                            \n                            \n                            \n                            30\n                                \n                                  \n                                  \n                                  \n                                \n                              \n                            \n                            \n                            \n                            \n                            \n                            \n                            \n                            \n                            \n                            \n                            \n                            \n                            \n                            \n                            \n                            \n                            \n                            \n                            \n                            \n                            \n                            \n                          \n                          \n                        \n                      \n                    \n                    \n                    \n\n                    \n  \n    規模の大きな主要花火大会\n  \n\n                  \n                  \n                  \n                \n              \n              \n              \n                          \n              \n                花火トピックス\n                全国の花火大会の開催・中止情報をお届け！注目の花火大会や、知って得する花火ネタをご紹介。\n              \n              \n                \n                  \n                  \n                      \n                      2025年も「金麦」“夏の味”の発売スタート！ほかの季節の金麦となにが違う？四季の味へのこだわりを聞いてみた\n                      \n                        PR\n                      \n                      全国\n                      \n                        2025年6月12日 10:00 更新\n                        \n                      \n                    \n                  \n                  \n                      \n                      「金麦」“夏の味”を編集部員が体験！ 「おうちで金麦花火セット」が当たるスペシャルなキャンペーンも紹介\n                      \n                        PR\n                      \n                      全国\n                      \n                        2025年6月12日 10:00 更新\n                        \n                      \n                    \n                  \n                  \n                      \n                      「日本三大花火大会」とは？日本最大規模の超大型花火大会をチェック！\n                      \n                        \n                      \n                      全国\n                      \n                        2025年6月11日 14:30 更新\n                        \n                      \n                    \n                  \n                \n              \n              \n                花火トピックスをもっと見る\n              \n            \n              \n                          \n              甲信越の花火大会を探す\n              \n                \n                  周辺のエリア・都道府県から探す\n                \n                \n                  \n                  山梨県\n                  \n                  長野県\n                  \n                  新潟県\n                  \n                \n\n                \n                \n                  開催状況から花火大会を探す\n                  \n                    開催予定の花火大会\n                    \n                  \n                \n                \n\n                花火カレンダーから探す\n                  \n\n                  \n                    \n                      \n                        \n                          甲信越の花火カレンダー\n                        \n                      \n                      \n                        \n                          今日開催の花火大会\n                        \n                      \n                      \n                        \n                          明日開催の花火大会\n                        \n                      \n                    \n                  \n\n                  開催される月から探す\n                    \n\n                    \n                        6月\n                      \n                        7月\n                      \n                        8月\n                      \n                        9月\n                      \n                        10月\n                      \n                        11月\n                      \n\n                ランキングから探す\n                \n                  \n                    \n                      \n                        甲信越の人気花火大会ランキング\n                      \n                      \n                        甲信越の行ってみたい花火大会ランキング\n                      \n                    \n                    \n                      \n                        甲信越の行ってよかった花火大会ランキング\n                      \n                      \n                        甲信越の打ち上げ数ランキング\n                      \n                    \n                    \n                      \n                        甲信越の人出ランキング\n                      \n                    \n                  \n                \n              \n            \n              \n                          \n              都道府県から花火大会を探す\n              \n                \n                  北海道\n                  北海道\n                \n                \n                  東　北\n                  宮城県\n                  青森県\n                  岩手県\n                  秋田県\n                  山形県\n                  福島県\n                \n                \n                  関　東\n                  東京都\n                  神奈川県\n                  千葉県\n                  埼玉県\n                  群馬県\n                  栃木県\n                  茨城県\n                \n                \n                  甲信越\n                  山梨県\n                  長野県\n                  新潟県\n                \n                \n                  北　陸\n                  石川県\n                  富山県\n                  福井県\n                \n                \n                  東　海\n                  愛知県\n                  岐阜県\n                  三重県\n                  静岡県\n                \n                \n                  関　西\n                  大阪府\n                  京都府\n                  兵庫県\n                  奈良県\n                  和歌山県\n                  滋賀県\n                \n                \n                  中　国\n                  広島県\n                  岡山県\n                  山口県\n                  鳥取県\n                  島根県\n                \n                \n                  四　国\n                  香川県\n                  愛媛県\n                  徳島県\n                  高知県\n                \n                \n                  九州・沖縄\n                  福岡県\n                  佐賀県\n                  長崎県\n                  熊本県\n                  大分県\n                  宮崎県\n                  鹿児島県\n                  沖縄県\n                \n              \n            \n              \n                       \n              花火特集2025\n              \n                花火大会をエリアから探す\n                \n                  北海道\n                  東北\n                  関東\n                  甲信越\n                  北陸\n                  東海\n                  関西\n                  中国\n                  四国\n                  九州・沖縄\n                \n\n                花火大会人気ランキング\n                \n                  全国\n                  北海道\n                  東北\n                  関東\n                  甲信越\n                  北陸\n                  東海\n                  関西\n                  中国\n                  四国\n                  九州・沖縄\n                \n                \n                \n                  打ち上げ数ランキング\n                  人出ランキング \n                  行ってみたいランキング\n                  行ってよかったランキング \n                \n                \n                \n                \n                \n                  花火大会カレンダー\n                  5月開催の花火大会\n                   6月開催の花火大会\n                    7月開催の花火大会\n                  8月開催の花火大会           \n                  9月開催の花火大会\n                  10月開催の花火大会\n                            \n                \n                \n               \n                  今日開催の花火大会\n                  明日開催の花火大会                  \n                 \n                \n                \n                  有料席のチケット情報\n                \n                \n                \n                  花火トピックス\n                \n                \n\n              \n            \n            \n            \n          \n          \n            \n\n\n\n\n\n\n\n\n            \n  おすすめ情報\n  \n\n\n\n\n\n\n\n\n\n\n\n\n\n\n\n\n\n\n\n\n\n\n  \n\n\n            \n            \n              人気花火大会ランキング【甲信越】\n                \n                  2025年6月14日 更新\n                  \n                    \n                        1\n                        第41回 咲花温泉水中花火大会\n                      \n                    \n                        2\n                        まき夏まつり 花火大会\n                      \n                    \n                        3\n                        河口湖湖上祭\n                      \n                    \n                        4\n                        長岡まつり大花火大会\n                      \n                    \n                        5\n                        長岡花火ローズファンタジー\n                      \n                  \n                  もっと見る \n                \n            \n            \n            \n              \n  閲覧履歴\n  \n    \n      \n        最近見た花火大会のページはありません。\n      \n    \n    閲覧履歴をもっと見る \n  \n\n            \n            \n  おすすめ記事\n  \n    \n      \n        \n          \n            \n            甲信越で今週末開催されるおすすめ花火大会\n          \n        \n      \n      \n    \n  \n\n                      \n            花火をもっと楽しむ\n            \n              \n\n                \n                  \n                  \n                    開催予定の花火大会\n                    2025年に開催予定の花火大会をご紹介\n                  \n                  \n                \n                  \n                  \n                    花火大会人気ランキング\n                    毎日更新！アクセス数の多い人気花火大会をエリア別にランキング\n                  \n                    \n                   \n                  \n                  \n                    有料席のチケット情報\n                    間近で上がる迫力満点の花火を座ってゆったり楽しもう！！\n                  \n                                         \n                  \n                  \n                  \n                    宿泊付き花火鑑賞ツアー販売中\n                    有料席とホテルをセットにしたウォーカー限定ツアーを販売中！！\n                  \n                   \n                                                   \n                  \n                   \n                  \n                  \n                    屋台のある花火大会をご紹介\n                    花火大会を盛り上げる屋台グルメを楽しめる人気の花火大会10選！\n                  \n                   \n                     \n                 \n                \n                  \n                  \n                    花火カレンダー\n                    花火大会の開催スケジュールをカレンダーでチェック！\n                  \n                  \n      \n                 \n                \n                \n\n                \n                  \n                  \n                    おでかけトピックス\n                    全国の花火大会の開催・中止情報をお届け！新しい花火の楽しみ方もご紹介。"
      },
      {
        "title": "信州の澄んだ夜空を彩る晩秋の花火",
        "date": "2025年11月23日",
        "location": "長野県・長野市/長野大橋西側",
        "visitors": "40万人",
        "fireworks": "",
        "rawText": "信州の澄んだ夜空を彩る晩秋の花火\n                          長野県・長野市/長野大橋西側  犀川第2緑地\n                          期間：2025年11月23日(日)\n                            \n                              例年の人出：約40万人\n                              行ってみたい：23\n                              行ってよかった：11\n                              \n                              有料席：あり\n                              屋台：あり"
      },
      {
        "title": "復興祈願花火フェニックスは、ほかにはない大迫力",
        "date": "2025年8月2日",
        "location": "新潟県・長岡市/信濃川河川敷",
        "visitors": "",
        "fireworks": "",
        "rawText": "復興祈願花火フェニックスは、ほかにはない大迫力\n                          新潟県・長岡市/信濃川河川敷\n                          期間：2025年8月2日(土)・3日(日)\n                            \n                              例年の人出：約34万5000人\n                              行ってみたい：81\n                              行ってよかった：42\n                              \n                              有料席：あり\n                              屋台：あり"
      },
      {
        "title": "日本一の大河「信濃川」を舞台に繰り広げられる壮大な花火大会",
        "date": "2025年8月10日",
        "location": "新潟県・新潟市中央区/新潟市中央区信濃川河畔(昭和大橋周辺)",
        "visitors": "32万人",
        "fireworks": "",
        "rawText": "日本一の大河「信濃川」を舞台に繰り広げられる壮大な花火大会\n                          新潟県・新潟市中央区/新潟市中央区信濃川河畔(昭和大橋周辺)\n                          期間：2025年8月10日(日)\n                            \n                              例年の人出：約32万人\n                              行ってみたい：20\n                              行ってよかった：7"
      },
      {
        "title": "全国新作花火チャレンジカップ2025",
        "date": "2025年9月6日",
        "location": "長野県・諏訪市/長野県諏訪市湖畔公園前諏訪湖上",
        "visitors": "25万人",
        "fireworks": "",
        "rawText": "全国新作花火チャレンジカップ2025\n                      \n                      \n                        \n                        \n                      \n                      \n                        \n                          6年ぶりにリニューアルし、分散方式による競技花火を開催決定\n                          長野県・諏訪市/長野県諏訪市湖畔公園前諏訪湖上\n                          期間：予選：2025年9月6日(土)・13日(土)・20日(土)・27日(土)。決勝：10月26日(日)\n                            \n                              例年の人出：約25万人\n                              行ってみたい：7\n                              行ってよかった：2"
      },
      {
        "title": "6年ぶりにリニューアルし、分散方式による競技花火を開催決定",
        "date": "2025年9月6日",
        "location": "長野県・諏訪市/長野県諏訪市湖畔公園前諏訪湖上",
        "visitors": "25万人",
        "fireworks": "",
        "rawText": "6年ぶりにリニューアルし、分散方式による競技花火を開催決定\n                          長野県・諏訪市/長野県諏訪市湖畔公園前諏訪湖上\n                          期間：予選：2025年9月6日(土)・13日(土)・20日(土)・27日(土)。決勝：10月26日(日)\n                            \n                              例年の人出：約25万人\n                              行ってみたい：7\n                              行ってよかった：2"
      },
      {
        "title": "市川三郷町ふるさと夏まつり　第37回「神明の花火大会」",
        "date": "2025年8月7日",
        "location": "山梨県・西八代郡市川三郷町/三郡橋下流笛吹川河畔",
        "visitors": "20万人",
        "fireworks": "2万発",
        "rawText": "市川三郷町ふるさと夏まつり　第37回「神明の花火大会」\n                      \n                      \n                        \n                        \n                      \n                      \n                        \n                          音楽と彩る約2万発の夜空の芸術\n                          山梨県・西八代郡市川三郷町/三郡橋下流笛吹川河畔\n                          期間：2025年8月7日(木)\n                            \n                              例年の人出：約20万人\n                              行ってみたい：28\n                              行ってよかった：20\n                              \n                              有料席：あり\n                              屋台：あり"
      },
      {
        "title": "第51回 阿賀野川ござれや花火",
        "date": "2025年8月25日",
        "location": "新潟県・新潟市北区/阿賀野川松浜橋上流側",
        "visitors": "20万人",
        "fireworks": "",
        "rawText": "第51回 阿賀野川ござれや花火\n                      \n                      \n                        \n                        \n                      \n                      \n                        \n                          超特大スターマインの花鳥風月をお見逃しなく\n                          新潟県・新潟市北区/阿賀野川松浜橋上流側\n                          期間：2025年8月25日(月)\n                            \n                              例年の人出：20万人\n                              行ってみたい：7\n                              行ってよかった：5\n                              \n                              有料席：あり"
      },
      {
        "title": "おぢやまつり大花火大会2024",
        "date": "2024年8月24日",
        "location": "新潟県・小千谷市/信濃川河川敷(旭橋下流)",
        "visitors": "18万人",
        "fireworks": "",
        "rawText": "おぢやまつり大花火大会2024\n                      \n                      \n                        \n                        \n                      \n                      \n                        \n                          超ワイド大スターマインが夜空に咲く\n                          新潟県・小千谷市/信濃川河川敷(旭橋下流)\n                          期間：2024年8月24日(土)おぢやまつりは8月23日(金)～25日(日)の3日間\n                            \n                              例年の人出：18万人\n                              行ってみたい：5\n                              行ってよかった：2\n                              \n                              有料席：あり"
      },
      {
        "title": "尺玉100発一斉打上など豪華な花火がめじろ押し",
        "date": "2025年7月26日",
        "location": "新潟県・柏崎市/柏崎市中央海岸・みなとまち海浜公園一帯",
        "visitors": "17万人",
        "fireworks": "100発",
        "rawText": "尺玉100発一斉打上など豪華な花火がめじろ押し\n                          新潟県・柏崎市/柏崎市中央海岸・みなとまち海浜公園一帯\n                          期間：2025年7月26日(土)\n                            \n                              例年の人出：約17万人\n                              行ってみたい：24\n                              行ってよかった：18\n                              \n                              有料席：あり\n                              屋台：あり"
      },
      {
        "title": "2025年も「金麦」“夏の味”の発売スタート！ほかの季節の金麦となにが違う？四季の味へのこだわりを聞いてみた",
        "date": "2025年6月12日",
        "location": "",
        "visitors": "",
        "fireworks": "",
        "rawText": "2025年も「金麦」“夏の味”の発売スタート！ほかの季節の金麦となにが違う？四季の味へのこだわりを聞いてみた\n                      \n                        PR\n                      \n                      全国\n                      \n                        2025年6月12日 10:00 更新\n                        \n                      \n                    \n                  \n                  \n                      \n                      「金麦」“夏の味”を編集部員が体験！ 「おうちで金麦花火セット」が当たるスペシャルなキャンペーンも紹介\n                      \n                        PR\n                      \n                      全国\n                      \n                        2025年6月12日 10:00 更新\n                        \n                      \n                    \n                  \n                  \n                      \n                      「日本三大花火大会」とは？日本最大規模の超大型花火大会をチェック！\n                      \n                        \n                      \n                      全国\n                      \n                        2025年6月11日 14:30 更新"
      },
      {
        "title": "「金麦」“夏の味”を編集部員が体験！ 「おうちで金麦花火セット」が当たるスペシャルなキャンペーンも紹介",
        "date": "2025年6月12日",
        "location": "",
        "visitors": "",
        "fireworks": "",
        "rawText": "「金麦」“夏の味”を編集部員が体験！ 「おうちで金麦花火セット」が当たるスペシャルなキャンペーンも紹介\n                      \n                        PR\n                      \n                      全国\n                      \n                        2025年6月12日 10:00 更新"
      },
      {
        "title": "「日本三大花火大会」とは？日本最大規模の超大型花火大会をチェック！",
        "date": "2025年6月11日",
        "location": "",
        "visitors": "",
        "fireworks": "",
        "rawText": "「日本三大花火大会」とは？日本最大規模の超大型花火大会をチェック！\n                      \n                        \n                      \n                      全国\n                      \n                        2025年6月11日 14:30 更新"
      },
      {
        "title": "人気花火大会ランキング【甲信越】",
        "date": "2025年6月14日",
        "location": "",
        "visitors": "",
        "fireworks": "",
        "rawText": "人気花火大会ランキング【甲信越】\n                \n                  2025年6月14日 更新\n                  \n                    \n                        1\n                        第41回 咲花温泉水中花火大会\n                      \n                    \n                        2\n                        まき夏まつり 花火大会\n                      \n                    \n                        3\n                        河口湖湖上祭\n                      \n                    \n                        4\n                        長岡まつり大花火大会\n                      \n                    \n                        5\n                        長岡花火ローズファンタジー\n                      \n                  \n                  もっと見る"
      },
      {
        "title": "2025年6月14日 更新",
        "date": "2025年6月14日",
        "location": "",
        "visitors": "",
        "fireworks": "",
        "rawText": "2025年6月14日 更新\n                  \n                    \n                        1\n                        第41回 咲花温泉水中花火大会\n                      \n                    \n                        2\n                        まき夏まつり 花火大会\n                      \n                    \n                        3\n                        河口湖湖上祭\n                      \n                    \n                        4\n                        長岡まつり大花火大会\n                      \n                    \n                        5\n                        長岡花火ローズファンタジー\n                      \n                  \n                  もっと見る"
      }
    ],
    "localOnly": [
      {
        "id": "kawaguchiko-kojosai-2025",
        "name": "河口湖湖上祭",
        "date": "2025年8月5日",
        "location": "山梨県・南都留郡富士河口湖町/河口湖畔船津浜",
        "visitors": 100000,
        "fireworks": 20000
      },
      {
        "id": "joetsu-matsuri-naoetsu-hanabi-2024",
        "name": "上越祭大花火大会(直江津地区)",
        "date": "2024年7月29日",
        "location": "新潟県・上越市/直江津港周边",
        "visitors": 100000,
        "fireworks": 20000
      },
      {
        "id": "niigata-matsuri-hanabi-2025",
        "name": "新潟祭花火大会",
        "date": "2025年8月10日",
        "location": "新潟県・新潟市中央区/信濃川河畔 昭和大橋西詰",
        "visitors": 320000,
        "fireworks": 4000
      },
      {
        "id": "sanjo-natsu-matsuri-hanabi-2024",
        "name": "三条市合并20周年纪念 第21回三条夏祭大花火大会",
        "date": "2024年8月4日",
        "location": "新潟県・三条市/信浓川河川敷",
        "visitors": 100000,
        "fireworks": 6000
      },
      {
        "id": "shinshu-ueda-dai-hanabi-2024",
        "name": "上田市诞生20周年纪念 第38回信州上田大花火大会",
        "date": "2024年8月5日",
        "location": "长野県・上田市/千曲川河川敷",
        "visitors": 120000,
        "fireworks": 2000
      }
    ]
  }
}